[{"name": "Svensk hel kyckling", "price": "25 kr/kg", "img": "https://d2rfo6yapuixuu.cloudfront.net/hc0/h3f/9822541643806/2359715300003_1580806236668_master_axfood_300", "displayVolume": "ca 1,35kg", "brand": "Garant"}, {"name": "Kycklingl\u00e5rfil\u00e9", "price": "3 f\u00f6r 99 kr", "img": "https://d2rfo6yapuixuu.cloudfront.net/h74/h7b/12010952294430/7340083490163_1629793275353_master_axfood_300", "displayVolume": "700g", "brand": "Eldorado"}, {"name": "Vegobacon", "price": "2 f\u00f6r 20 kr", "img": "https://d2rfo6yapuixuu.cloudfront.net/hf3/h61/9312449265694/7340083468391_1545229828204_master_axfood_300", "displayVolume": "120g", "brand": "Eldorado", "code": "101277028_ST", "link": "https://www.hemkop.se/produkt/Vegobacon-101277028_ST", "savePrice": "Spara 8,95 kr!"}, {"name": "Skogaholmslimpa", "price": "20 kr/st", "img": "https://d2rfo6yapuixuu.cloudfront.net/h63/haf/11441871028254/7312200010110_1617008428808_master_axfood_300", "displayVolume": "775g", "brand": "Skogaholm", "code": "101258242_ST", "link": "https://www.hemkop.se/produkt/Skogaholmslimpa-101258242_ST", "savePrice": "Spara 4,95 kr!"}, {"name": "Vitl\u00f6ksbaguetter", "price": "2 f\u00f6r 25 kr", "img": "https://d2rfo6yapuixuu.cloudfront.net/he6/h0e/8883507134494/07311041069059.jpg_1481185882220_master_axfood_300", "displayVolume": "2x175g", "brand": "Garant", "code": "101182511_ST", "link": "https://www.hemkop.se/produkt/Vitl\u00f6ksbaguetter-101182511_ST", "savePrice": "Spara 5,45 kr!"}, {"name": "Snabbkaffe", "price": "35 kr/st", "img": "https://d2rfo6yapuixuu.cloudfront.net/h7e/h3d/9143047553054/7340083409738_1527556289327_master_axfood_300", "displayVolume": "200g", "brand": "Garant", "code": "101201964_ST", "link": "https://www.hemkop.se/produkt/Snabbkaffe-101201964_ST", "savePrice": "Spara 10,95 kr!"}, {"name": "Juice", "price": "20 kr/st", "img": "https://d2rfo6yapuixuu.cloudfront.net/h41/hef/11510116024350/7340083480263_1618404619100_master_axfood_300", "displayVolume": "1l", "jfr pris": null, "brand": "Garant", "code": "101328354_ST", "link": "https://www.hemkop.se/produkt/Juice-101328354_ST", "savePrice": "Spara 7,95 kr!"}, {"name": "Ishavsr\u00e4kor", "price": "49 kr/st", "img": "https://d2rfo6yapuixuu.cloudfront.net/hb9/h49/11353907789854/7340083485930_1615546829302_master_axfood_300", "displayVolume": "750g", "brand": "Garant", "code": "101330214_ST", "link": "https://www.hemkop.se/produkt/Ishavsr\u00e4kor-101330214_ST", "savePrice": "Spara 20,95 kr!"}, {"name": "Duschkr\u00e4m, schampo 2-in-1", "price": "10 kr/st", "img": "https://d2rfo6yapuixuu.cloudfront.net/hbb/h59/12001772896286/7340083489112_1629464424707_master_axfood_300", "displayVolume": "300ml", "brand": "Mevolution", "code": "101339866_ST", "link": "https://www.hemkop.se/produkt/Duschkr\u00e4m,-schampo-2-in-1-101339866_ST", "savePrice": "Spara 4,95 kr!"}, {"name": "Tandkr\u00e4m", "price": "2 f\u00f6r 35 kr", "img": "https://d2rfo6yapuixuu.cloudfront.net/h22/hf8/9946332463134/8710908842528_1585442134972_master_axfood_300", "displayVolume": "75ml", "brand": "Zendium", "code": "101264096_ST", "link": "https://www.hemkop.se/produkt/Tandkr\u00e4m-101264096_ST", "savePrice": "Spara 7,45 kr!"}, {"name": "Jasminris", "price": "39 kr/st", "img": "https://d2rfo6yapuixuu.cloudfront.net/h2d/h8c/12041036496926/7340083482137_1630506664913_master_axfood_300", "displayVolume": "2kg", "brand": "Garant", "code": "101316061_ST", "link": "https://www.hemkop.se/produkt/Jasminris-101316061_ST", "savePrice": "Spara 10,95 kr!"}, {"name": "Maskindisktabletter", "price": "30 kr/st", "img": "https://d2rfo6yapuixuu.cloudfront.net/ha2/h03/10297523732510/7340083459139_1594366527555_master_axfood_300", "displayVolume": "30-pack", "brand": "S\u00e5klart", "code": "101261849_ST", "link": "https://www.hemkop.se/produkt/Maskindisktabletter-101261849_ST", "savePrice": "Spara 7,95 kr!"}, {"name": "Reng\u00f6ringsspray", "price": "15 kr/st", "img": "https://d2rfo6yapuixuu.cloudfront.net/h4b/ha4/8943531556894/07340083459160.jpg_1498943199646_master_axfood_300", "displayVolume": "500-750ml", "brand": "S\u00e5klart", "code": "101261856_ST", "link": "https://www.hemkop.se/produkt/Reng\u00f6ringsspray-101261856_ST", "savePrice": "Spara 4,95 kr!"}, {"name": "Yoggi", "price": "15 kr/st", "img": "https://d2rfo6yapuixuu.cloudfront.net/hfa/h67/10401028309022/7310865052681_1597391453607_master_axfood_300", "displayVolume": "1kg", "jfr pris": null, "brand": "Arla", "code": "100049877_ST", "link": "https://www.hemkop.se/produkt/Yoggi-100049877_ST", "savePrice": "Spara 7,50 kr!"}, {"name": "K\u00f6ttbullar", "price": "10 kr/st", "img": "https://d2rfo6yapuixuu.cloudfront.net/h1b/hcf/9284136665118/7311041056387_1542634828938_master_axfood_300", "displayVolume": "350g", "brand": "Garant", "code": "101066052_ST", "link": "https://www.hemkop.se/produkt/K\u00f6ttbullar-101066052_ST", "savePrice": "Spara 9,95 kr!"}, {"name": "Pulled pork", "price": "35 kr/st", "img": "https://d2rfo6yapuixuu.cloudfront.net/h11/h81/8928997179422/07340083437564.jpg_1495112459190_master_axfood_300", "displayVolume": "550g", "brand": "Garant", "code": "101226963_ST", "link": "https://www.hemkop.se/produkt/Pulled-pork-101226963_ST", "savePrice": "Spara 24,95 kr!"}, {"name": "Tv\u00e4ttmedel, sk\u00f6ljmedel", "price": "25 kr/st", "img": "https://d2rfo6yapuixuu.cloudfront.net/h38/h8f/11424383008798/8717644814499_1616680849750_master_axfood_300", "displayVolume": "750g, 0,5-1l", "brand": "Comfort", "code": "100916234_ST", "link": "https://www.hemkop.se/produkt/Tv\u00e4ttmedel,-sk\u00f6ljmedel-100916234_ST", "savePrice": "Spara 2,95 kr!"}, {"name": "Gouda", "price": "39,95 kr/kg", "img": "https://d2rfo6yapuixuu.cloudfront.net/h77/hc2/8857893371934/02359742700005.jpg_master_axfood_300", "displayVolume": "ca 1,2-2,2kg", "jfr pris": null, "brand": "Eldorado"}, {"name": "Helgbukett", "price": "99 kr/st", "img": "https://d2rfo6yapuixuu.cloudfront.net/h17/he3/12318606491678/7311042010616_1637853918761_master_axfood_300", "displayVolume": null, "jfr pris": null, "brand": null, "code": "101314726_ST", "link": "https://www.hemkop.se/produkt/Helgbukett-101314726_ST", "savePrice": "Spara 30,00 kr!"}, {"name": "Kalanchoe", "price": "29,95 kr/st", "img": "https://d2rfo6yapuixuu.cloudfront.net/hc0/h8f/9509768691742/7311042009863_1561409160276_master_axfood_300", "displayVolume": null, "jfr pris": null, "brand": null}, {"name": "Broccoli", "price": "5 kr/st", "img": "https://d2rfo6yapuixuu.cloudfront.net/h34/h85/9004105531422/07311042017110.jpg_1510423884945_master_axfood_300", "displayVolume": "250g", "brand": null, "code": "101274134_ST", "link": "https://www.hemkop.se/produkt/Broccoli-101274134_ST", "savePrice": "Spara 6,95 kr!"}, {"name": "Gurka", "price": "10 kr/st", "img": "https://d2rfo6yapuixuu.cloudfront.net/h94/h28/8854938124318/07311042005186.jpg_master_axfood_300", "displayVolume": "320g", "brand": null, "code": "100594956_ST", "link": "https://www.hemkop.se/produkt/Gurka-100594956_ST", "savePrice": "Spara 4,95 kr!"}, {"name": "Citroner", "price": "10 kr/st", "img": "https://d2rfo6yapuixuu.cloudfront.net/h11/h61/8855380688926/07311042000280.jpg_master_axfood_300", "displayVolume": "500g", "brand": null, "code": "100946979_ST", "link": "https://www.hemkop.se/produkt/Citroner-100946979_ST", "savePrice": "Spara 7,95 kr!"}, {"name": "Blodapelsiner", "price": "20 kr/st", "img": "https://d2rfo6yapuixuu.cloudfront.net/h20/h16/8854373269534/07311042005568.jpg_master_axfood_300", "displayVolume": "1kg", "jfr pris": null, "brand": null, "code": "100243531_ST", "link": "https://www.hemkop.se/produkt/Blodapelsiner-100243531_ST", "savePrice": "Spara 6,95 kr!"}, {"name": "P\u00e4ron Carola", "price": "20 kr/kg", "img": "https://d2rfo6yapuixuu.cloudfront.net/h3a/h94/8854180855838/07311042005308.jpg_master_axfood_300", "displayVolume": "ca: 170g", "jfr pris": null, "brand": null}, {"name": "F\u00e4rsk sushilax", "price": "69,95 kr/st", "img": "https://d2rfo6yapuixuu.cloudfront.net/hea/hde/12154556186654/7340083483226_1633523726844_master_axfood_300", "displayVolume": "180g", "brand": "Falkenberg", "code": "101320779_ST", "link": "https://www.hemkop.se/produkt/F\u00e4rsk-sushilax-101320779_ST", "savePrice": "Spara 17,05 kr!"}, {"name": "R\u00e4kor", "price": "59,95 kr/st", "img": "https://d2rfo6yapuixuu.cloudfront.net/hf8/h26/8933433409566/07340083458781.jpg_1496320850098_master_axfood_300", "displayVolume": "500g", "brand": "Falkenberg", "code": "101267945_ST", "link": "https://www.hemkop.se/produkt/R\u00e4kor-101267945_ST", "savePrice": "Spara 29,05 kr!"}, {"name": "Grillade kycklingl\u00e5r 2 f\u00f6r 15", "price": "15 kr/st", "img": "https://d2rfo6yapuixuu.cloudfront.net/h3c/h78/12441130926110/Grillade kycklingl\u00e5r_v1_axfood_300", "displayVolume": null, "jfr pris": null, "brand": "Guldf\u00e5geln"}, {"name": "Svensk fl\u00e4skkotlett", "price": "69,95 kr/kg", "img": "https://d2rfo6yapuixuu.cloudfront.net/hcd/h56/10832195485726/2320051900004_1606895074383_master_axfood_300", "displayVolume": "ca 830g", "jfr pris": null, "brand": "Scan"}, {"name": "Svensk l\u00f6vbiff", "price": "169 kr/kg", "img": "https://d2rfo6yapuixuu.cloudfront.net/h0f/h11/8920171675678/02355001900001.jpg_1492788064041_master_axfood_300", "displayVolume": "ca 450-850g", "jfr pris": null, "brand": "Garant"}, {"name": "Svensk skinkstek", "price": "59,95 kr/kg", "img": "https://d2rfo6yapuixuu.cloudfront.net/h5b/h8e/11602487771166/2330048600008_1619690774939_master_axfood_300", "displayVolume": "ca 1,0kg", "jfr pris": null, "brand": "Dalsj\u00f6fors"}, {"name": "Marmelad", "price": "18,95 kr/st", "img": "https://d2rfo6yapuixuu.cloudfront.net/h5b/ha8/8857587712030/07340083435362.jpg_master_axfood_300", "displayVolume": "400g", "brand": "Garant", "code": "101224589_ST", "link": "https://www.hemkop.se/produkt/Marmelad-101224589_ST", "savePrice": "Spara 5,00 kr!"}, {"name": "Olivolja Classico", "price": "39,95 kr/st", "img": "https://d2rfo6yapuixuu.cloudfront.net/h5f/hca/9517609975838/7340083474194_1562100033704_master_axfood_300", "displayVolume": "500ml", "brand": "Garant", "code": "101290879_ST", "link": "https://www.hemkop.se/produkt/Olivolja-Classico-101290879_ST", "savePrice": "Spara 5,00 kr!"}, {"name": "Fond", "price": "23,95 kr/st", "img": "https://d2rfo6yapuixuu.cloudfront.net/hfe/h8a/8857152225310/07340083430244.jpg_master_axfood_300", "displayVolume": "180ml ger 4l f\u00e4rdig buljong", "brand": "Garant", "code": "101213738_ST", "link": "https://www.hemkop.se/produkt/Fond-101213738_ST", "savePrice": "Spara 4,00 kr!"}, {"name": "Dijonsenap", "price": "15 kr/st", "img": "https://d2rfo6yapuixuu.cloudfront.net/he7/h33/11818149150750/7340083486814_1623920728673_master_axfood_300", "displayVolume": "200g", "brand": "Garant", "code": "101332038_ST", "link": "https://www.hemkop.se/produkt/Dijonsenap-101332038_ST", "savePrice": "Spara 3,95 kr!"}, {"name": "Branflakes, Specialflingor", "price": "20 kr/st", "img": "https://d2rfo6yapuixuu.cloudfront.net/h53/h0a/9518392868894/7340083475665_1562187134182_master_axfood_300", "displayVolume": "500g", "brand": "Garant", "code": "101294580_ST", "link": "https://www.hemkop.se/produkt/Branflakes,-Specialflingor-101294580_ST", "savePrice": "Spara 3,95 kr!"}, {"name": "Wokmix", "price": "15 kr/st", "img": "https://d2rfo6yapuixuu.cloudfront.net/h8e/he3/11262382211102/7340083484582_1614116445708_master_axfood_300", "displayVolume": "500g", "brand": "Garant", "code": "101328926_ST", "link": "https://www.hemkop.se/produkt/Wokmix-101328926_ST", "savePrice": "Spara 5,95 kr!"}, {"name": "Salami", "price": "22,95 kr/st", "img": "https://d2rfo6yapuixuu.cloudfront.net/h6b/hdd/11412006109214/5701251858543_1616518265335_master_axfood_300", "displayVolume": "150g", "brand": "G\u00f8l", "code": "100191141_ST", "link": "https://www.hemkop.se/produkt/Salami-100191141_ST", "savePrice": "Spara 3,00 kr!"}, {"name": "Getost", "price": "25 kr/st", "img": "https://d2rfo6yapuixuu.cloudfront.net/ha0/hfc/8894866489374/07340083453793.jpg_1485275719545_master_axfood_300", "displayVolume": "180g", "brand": "Garant", "code": "101260329_ST", "link": "https://www.hemkop.se/produkt/Getost-101260329_ST", "savePrice": "Spara 8,50 kr!"}, {"name": "\u00c4gg 20-pack", "price": "44,95 kr/st", "img": "https://d2rfo6yapuixuu.cloudfront.net/hdb/hfc/11789094027294/7340083474675_1623276374777_master_axfood_300", "displayVolume": "20p", "brand": "Garant", "code": "101285696_ST", "link": "https://www.hemkop.se/produkt/\u00c4gg-20-pack-101285696_ST", "savePrice": "Spara 7,00 kr!"}, {"name": "Kvarg", "price": "6 kr/st", "img": "https://d2rfo6yapuixuu.cloudfront.net/h40/ha4/11776149553182/7392672001724_1623069347270_master_axfood_300", "displayVolume": "150g", "brand": "Lindahls", "code": "101224058_ST", "link": "https://www.hemkop.se/produkt/Kvarg-101224058_ST", "savePrice": "Spara 2,95 kr!"}, {"name": "V\u00e4rmeljus 50-pack", "price": "34,95 kr/st", "img": "https://d2rfo6yapuixuu.cloudfront.net/h5a/hdb/9563705671710/7340083475337_1566852360952_master_axfood_300", "displayVolume": "50p", "brand": "Fixa", "code": "101294197_ST", "link": "https://www.hemkop.se/produkt/V\u00e4rmeljus-50-pack-101294197_ST", "savePrice": "Spara 5,00 kr!"}, {"name": "Rakhyvelset", "price": "39,95 kr/st", "img": "https://d2rfo6yapuixuu.cloudfront.net/h90/hd2/11827643547678/7340083489396_1624135531675_master_axfood_300", "displayVolume": "1-pack", "jfr pris": null, "brand": "Mevolution", "code": "101339967_ST", "link": "https://www.hemkop.se/produkt/Rakhyvelset-101339967_ST", "savePrice": "Spara 10,00 kr!"}, {"name": "Pizzakit", "price": "18,95 kr/st", "img": "https://d2rfo6yapuixuu.cloudfront.net/h1b/h84/8874297131038/07611612142007.jpg_1474978904600_master_axfood_300", "displayVolume": "600g", "brand": "Monte Castello", "code": "101255490_ST", "link": "https://www.hemkop.se/produkt/Pizzakit-101255490_ST", "savePrice": "Spara 3,00 kr!"}, {"name": "Potatisgrat\u00e4ng", "price": "20 kr/st", "img": "https://d2rfo6yapuixuu.cloudfront.net/h3c/h64/10454884024350/7340083482557_1598734029761_master_axfood_300", "displayVolume": "800g", "brand": "Garant", "code": "101315662_ST", "link": "https://www.hemkop.se/produkt/Potatisgrat\u00e4ng-101315662_ST", "savePrice": "Spara 2,95 kr!"}, {"name": "R\u00e5gbr\u00f6d", "price": "10 kr/st", "img": "https://d2rfo6yapuixuu.cloudfront.net/h2b/hd4/9256754249758/7340083463907_1539787840031_master_axfood_300", "displayVolume": "300-340g", "brand": "Garant", "code": "101273778_ST", "link": "https://www.hemkop.se/produkt/R\u00e5gbr\u00f6d-101273778_ST", "savePrice": "Spara 8,95 kr!"}, {"name": "Croissant, Pain au chocolat", "price": "5 kr/st", "img": "https://d2rfo6yapuixuu.cloudfront.net/h20/h09/8855666753566/7310960856245.jpg_master_axfood_300", "displayVolume": "60-90g", "brand": "Dafg\u00e5rd", "code": "101064599_ST", "link": "https://www.hemkop.se/produkt/Croissant,-Pain-au-chocolat-101064599_ST", "savePrice": "Spara 4,95 kr!"}, {"name": "Kylda s\u00e5ser, dressingar", "price": "2 f\u00f6r 25 kr", "img": "https://d2rfo6yapuixuu.cloudfront.net/hfb/h0b/8857604489246/07340083436222.jpg_master_axfood_300", "displayVolume": "200-220ml", "brand": "Garant", "code": "101224830_ST", "link": "https://www.hemkop.se/produkt/Kylda-s\u00e5ser,-dressingar-101224830_ST", "savePrice": "Spara 5,45 kr!"}, {"name": "Surdegsbaguetter", "price": "2 f\u00f6r 25 kr", "img": "https://d2rfo6yapuixuu.cloudfront.net/hdb/h1a/9968156213278/7340083480829_1585946602153_master_axfood_300", "displayVolume": "250g", "brand": "Garant", "code": "101308580_ST", "link": "https://www.hemkop.se/produkt/Surdegsbaguetter-101308580_ST", "savePrice": "Spara 2,45 kr!"}, {"name": "L\u00e4tta", "price": "2 f\u00f6r 35 kr", "img": "https://d2rfo6yapuixuu.cloudfront.net/h55/hb1/12150629990430/8719200212626_1633434340388_master_axfood_300", "displayVolume": "600g", "brand": "L\u00e4tta", "code": "101349965_ST", "link": "https://www.hemkop.se/produkt/L\u00e4tta-101349965_ST", "savePrice": "Spara 3,45 kr!"}, {"name": "Profeel pudding, milkshake", "price": "2 f\u00f6r 28 kr", "img": "https://d2rfo6yapuixuu.cloudfront.net/h7d/h93/11484771352606/6408430407675_1617828364553_master_axfood_300", "displayVolume": "180-250g", "brand": "Valio", "code": "101340616_ST", "link": "https://www.hemkop.se/produkt/Profeel-pudding,-milkshake-101340616_ST", "savePrice": "Spara 1,95 kr!"}, {"name": "Kaviar", "price": "2 f\u00f6r 25 kr", "img": "https://d2rfo6yapuixuu.cloudfront.net/h45/hd4/12081722359838/7340083401206_1631609422533_master_axfood_300", "displayVolume": "250g", "brand": "Garant", "code": "101191980_ST", "link": "https://www.hemkop.se/produkt/Kaviar-101191980_ST", "savePrice": "Spara 6,45 kr!"}, {"name": "GULASCH FELIX", "price": "32,95 kr/st", "img": "https://d2rfo6yapuixuu.cloudfront.net/h25/h5a/11486865031198/7310240064377_1617880582411_master_axfood_300", "displayVolume": "560g", "jfr pris": null, "brand": "Felix", "code": "100592823_ST", "link": "https://www.hemkop.se/produkt/GULASCH-FELIX-100592823_ST", "savePrice": "Spara 0,00 kr!"}, {"name": "COUSCOUS", "price": "24,95 kr/st", "img": "https://d2rfo6yapuixuu.cloudfront.net/h7c/h26/9868623151134/7340083478116_1582713631310_master_axfood_300", "displayVolume": "1000g", "jfr pris": null, "brand": "Garant", "code": "101301624_ST", "link": "https://www.hemkop.se/produkt/COUSCOUS-101301624_ST", "savePrice": "Spara 0,00 kr!"}, {"name": "BREGOTT EKO", "price": "51,95 kr/st", "img": "https://d2rfo6yapuixuu.cloudfront.net/h5b/h91/11717483823134/7310860560662_1621893980693_master_axfood_300", "displayVolume": "600g", "jfr pris": null, "brand": "Bregott", "code": "101002861_ST", "link": "https://www.hemkop.se/produkt/BREGOTT-EKO-101002861_ST", "savePrice": "Spara 0,00 kr!"}, {"name": "SKALADE R\u00c4KOR", "price": "49,95 kr/st", "img": "https://d2rfo6yapuixuu.cloudfront.net/h24/h05/10399269027870/7340083482304_1597351923116_master_axfood_300", "displayVolume": "200g", "jfr pris": null, "brand": "Garant", "code": "101319816_ST", "link": "https://www.hemkop.se/produkt/SKALADE-R\u00c4KOR-101319816_ST", "savePrice": "Spara 0,00 kr!"}, {"name": "EKO K\u00d6TTBULLAR", "price": "36,95 kr/st", "img": "https://d2rfo6yapuixuu.cloudfront.net/h89/h24/10832222158878/7300299061007_1606895260248_master_axfood_300", "displayVolume": "400g", "jfr pris": null, "brand": "Scan", "code": "101287699_ST", "link": "https://www.hemkop.se/produkt/EKO-K\u00d6TTBULLAR-101287699_ST", "savePrice": "Spara 0,00 kr!"}, {"name": "GRILLKORV", "price": "23,95 kr/st", "img": "https://d2rfo6yapuixuu.cloudfront.net/h67/hc6/9505610203166/7340083465017_1560948928480_master_axfood_300", "displayVolume": "400g", "jfr pris": null, "brand": "Garant", "code": "101276779_ST", "link": "https://www.hemkop.se/produkt/GRILLKORV-101276779_ST", "savePrice": "Spara 0,00 kr!"}, {"name": "HUSH\u00c5LLSOST", "price": "64,95 kr/kg", "img": "https://d2rfo6yapuixuu.cloudfront.net/h35/h69/8862129618974/02359746100009.jpg_master_axfood_300", "displayVolume": "ca: 2kg", "jfr pris": null, "brand": "Eldorado"}, {"name": "KYCKLINGF\u00c4RS", "price": "39,95 kr/st", "img": "https://d2rfo6yapuixuu.cloudfront.net/hba/hd7/8962017591326/07340083455858.jpg_1503560149443_master_axfood_300", "displayVolume": "500g", "jfr pris": null, "brand": "Garant", "code": "101262973_ST", "link": "https://www.hemkop.se/produkt/KYCKLINGF\u00c4RS-101262973_ST", "savePrice": "Spara 2,00 kr!"}, {"name": "N\u00c4SDUKAR", "price": "19,95 kr/st", "img": "https://d2rfo6yapuixuu.cloudfront.net/h5d/h7a/10545077911582/7316970580002_1601020220684_master_axfood_300", "displayVolume": "100st", "jfr pris": null, "brand": "Lambi", "code": "100348553_ST", "link": "https://www.hemkop.se/produkt/N\u00c4SDUKAR-100348553_ST", "savePrice": "Spara 0,00 kr!"}, {"name": "EKO KAVIAR", "price": "18,95 kr/st", "img": "https://d2rfo6yapuixuu.cloudfront.net/ha5/he5/12081722884126/7340083440700_1631609424459_master_axfood_300", "displayVolume": "190g", "jfr pris": null, "brand": "Garant", "code": "101232334_ST", "link": "https://www.hemkop.se/produkt/EKO-KAVIAR-101232334_ST", "savePrice": "Spara 0,00 kr!"}, {"name": "EKO OLIVOLJA SPANSK", "price": "49,95 kr/st", "img": "https://d2rfo6yapuixuu.cloudfront.net/hdf/h80/9064228388894/07340083463785.jpg_1518015016585_master_axfood_300", "displayVolume": "500ml", "jfr pris": null, "brand": "Garant Eko", "code": "101274043_ST", "link": "https://www.hemkop.se/produkt/EKO-OLIVOLJA-SPANSK-101274043_ST", "savePrice": "Spara 0,00 kr!"}, {"name": "VISPGR\u00c4DDE 5DL", "price": "22,95 kr/st", "img": "https://d2rfo6yapuixuu.cloudfront.net/h4a/hc6/9045188247582/07311041065013.jpg_1515775249871_master_axfood_300", "displayVolume": "5dl", "jfr pris": null, "brand": "Garant", "code": "101173865_ST", "link": "https://www.hemkop.se/produkt/VISPGR\u00c4DDE-5DL-101173865_ST", "savePrice": "Spara 0,00 kr!"}, {"name": "OMEGA LAX", "price": "89 kr/st", "img": "https://d2rfo6yapuixuu.cloudfront.net/h79/h5c/9560664145950/7340083455889_1566560548665_master_axfood_300", "displayVolume": "4x125g", "jfr pris": null, "brand": "Omega", "code": "101263061_ST", "link": "https://www.hemkop.se/produkt/OMEGA-LAX-101263061_ST", "savePrice": "Spara 0,00 kr!"}, {"name": "FRIA TOAST", "price": "28,95 kr/st", "img": "https://d2rfo6yapuixuu.cloudfront.net/h41/h7f/9349010653214/7330242240012_1548552091947_master_axfood_300", "displayVolume": "500g", "jfr pris": null, "brand": "Fria", "code": "101287810_ST", "link": "https://www.hemkop.se/produkt/FRIA-TOAST-101287810_ST", "savePrice": "Spara 0,00 kr!"}, {"name": "FRIA FORMBR\u00d6D", "price": "28,95 kr/st", "img": "https://d2rfo6yapuixuu.cloudfront.net/h48/hde/9349011308574/7330242240050_1548552097711_master_axfood_300", "displayVolume": "500g", "jfr pris": null, "brand": "Fria", "code": "101287806_ST", "link": "https://www.hemkop.se/produkt/FRIA-FORMBR\u00d6D-101287806_ST", "savePrice": "Spara 0,00 kr!"}, {"name": "FRIA GROVA FORMBR\u00d6D", "price": "28,95 kr/st", "img": "https://d2rfo6yapuixuu.cloudfront.net/h87/h09/12114398609438/7330242200313_1632694270717_master_axfood_300", "displayVolume": "500g", "jfr pris": null, "brand": "Fria", "code": "101287793_ST", "link": "https://www.hemkop.se/produkt/FRIA-GROVA-FORMBR\u00d6D-101287793_ST", "savePrice": "Spara 0,00 kr!"}, {"name": "TRIUMF GLASS 2L", "price": "37,95 kr/st", "img": "https://d2rfo6yapuixuu.cloudfront.net/hc4/h1b/9400763482142/7312060005417_1552557973851_master_axfood_300", "displayVolume": "2l", "jfr pris": null, "brand": "Triumf Glass", "code": "100361467_ST", "link": "https://www.hemkop.se/produkt/TRIUMF-GLASS-2L-100361467_ST", "savePrice": "Spara 0,00 kr!"}, {"name": "PUMPAK\u00c4RNOR", "price": "56,95 kr/st", "img": "https://d2rfo6yapuixuu.cloudfront.net/h79/hde/8873777823774/07340083450624.jpg_1474464085758_master_axfood_300", "displayVolume": "800g", "jfr pris": null, "brand": "Eldorado", "code": "101250209_ST", "link": "https://www.hemkop.se/produkt/PUMPAK\u00c4RNOR-101250209_ST", "savePrice": "Spara 0,00 kr!"}, {"name": "SOLROSK\u00c4RNOR", "price": "26,95 kr/st", "img": "https://d2rfo6yapuixuu.cloudfront.net/h9a/hd1/8873777496094/07340083450617.jpg_1474464080320_master_axfood_300", "displayVolume": "800g", "jfr pris": null, "brand": "Eldorado", "code": "101250208_ST", "link": "https://www.hemkop.se/produkt/SOLROSK\u00c4RNOR-101250208_ST", "savePrice": "Spara 0,00 kr!"}, {"name": "LINSER GR\u00d6NA", "price": "19,95 kr/st", "img": "https://d2rfo6yapuixuu.cloudfront.net/h44/h20/10112033980446/7340083481314_1589541041777_master_axfood_300", "displayVolume": "800g", "jfr pris": null, "brand": "Eldorado", "code": "101334234_ST", "link": "https://www.hemkop.se/produkt/LINSER-GR\u00d6NA-101334234_ST", "savePrice": "Spara 0,00 kr!"}, {"name": "LINSER R\u00d6DA", "price": "19,95 kr/st", "img": "https://d2rfo6yapuixuu.cloudfront.net/ha4/h12/10112033587230/7340083481307_1589541040247_master_axfood_300", "displayVolume": "800g", "jfr pris": null, "brand": "Eldorado", "code": "101310192_ST", "link": "https://www.hemkop.se/produkt/LINSER-R\u00d6DA-101310192_ST", "savePrice": "Spara 0,00 kr!"}, {"name": "B\u00d6NOR VITA SM\u00c5", "price": "26,95 kr/st", "img": "https://d2rfo6yapuixuu.cloudfront.net/h2d/hd2/8873773596702/07340083450563.jpg_1474463190956_master_axfood_300", "displayVolume": "800g", "jfr pris": null, "brand": "Eldorado", "code": "101334235_ST", "link": "https://www.hemkop.se/produkt/B\u00d6NOR-VITA-SM\u00c5-101334235_ST", "savePrice": "Spara 0,00 kr!"}, {"name": "KIK\u00c4RTER", "price": "27,95 kr/st", "img": "https://d2rfo6yapuixuu.cloudfront.net/hbc/hdc/8873773269022/07340083450556.jpg_1474463180521_master_axfood_300", "displayVolume": "800g", "jfr pris": null, "brand": "Eldorado", "code": "101250199_ST", "link": "https://www.hemkop.se/produkt/KIK\u00c4RTER-101250199_ST", "savePrice": "Spara 0,00 kr!"}, {"name": "DIGESTIVE", "price": "12,95 kr/st", "img": "https://d2rfo6yapuixuu.cloudfront.net/h81/hfa/9599533154334/7340083470790_1569222468488_master_axfood_300", "displayVolume": "400g", "jfr pris": null, "brand": "Garant", "code": "101289590_ST", "link": "https://www.hemkop.se/produkt/DIGESTIVE-101289590_ST", "savePrice": "Spara 0,00 kr!"}, {"name": "LEVAINBR\u00d6D", "price": "34,95 kr/st", "img": "https://d2rfo6yapuixuu.cloudfront.net/h82/h9c/8862588108830/07310960026426.jpg_master_axfood_300", "displayVolume": "800g", "jfr pris": null, "brand": "Dafg\u00e5rd", "code": "101249098_ST", "link": "https://www.hemkop.se/produkt/LEVAINBR\u00d6D-101249098_ST", "savePrice": "Spara 0,00 kr!"}, {"name": "EKO TORSKFIL\u00c9", "price": "49,95 kr/st", "img": "https://d2rfo6yapuixuu.cloudfront.net/h91/h53/8855311482910/7340083407147.jpg_master_axfood_300", "displayVolume": "400g", "jfr pris": null, "brand": "Garant", "code": "100911612_ST", "link": "https://www.hemkop.se/produkt/EKO-TORSKFIL\u00c9-100911612_ST", "savePrice": "Spara 0,00 kr!"}, {"name": "GAR H\u00c5RDOST", "price": "84,95 kr/kg", "img": "https://d2rfo6yapuixuu.cloudfront.net/h77/had/8866131279902/02359723900004.jpg_1465291222129_master_axfood_300", "displayVolume": "ca: 700g", "jfr pris": null, "brand": "Garant"}, {"name": "EKO BANAN", "price": "23,95 kr/kg", "img": "https://d2rfo6yapuixuu.cloudfront.net/h7a/hdc/10598017859614/7311042004714_1602249053286_master_axfood_300", "displayVolume": "ca: 170g", "jfr pris": null, "brand": null}, {"name": "VEG F\u00c4RS", "price": "64,95 kr/st", "img": "https://d2rfo6yapuixuu.cloudfront.net/hf0/h2e/10666920476702/7310240121117_1603888562996_master_axfood_300", "displayVolume": "1kg", "jfr pris": null, "brand": "Anamma", "code": "101275800_ST", "link": "https://www.hemkop.se/produkt/VEG-F\u00c4RS-101275800_ST", "savePrice": "Spara 0,00 kr!"}, {"name": "TURKISK YOGHURT", "price": "26,95 kr/st", "img": "https://d2rfo6yapuixuu.cloudfront.net/hc5/he1/11780335239198/7392672104104_1623144052136_master_axfood_300", "displayVolume": "1kg", "jfr pris": null, "brand": "Salakis", "code": "100486886_ST", "link": "https://www.hemkop.se/produkt/TURKISK-YOGHURT-100486886_ST", "savePrice": "Spara 0,00 kr!"}, {"name": "SM\u00d6R & RAPS", "price": "41,95 kr/st", "img": "https://d2rfo6yapuixuu.cloudfront.net/h6d/h6d/8891825225758/07340083447983.jpg_1484432062782_master_axfood_300", "displayVolume": "600g", "jfr pris": null, "brand": "Garant", "code": "101244335_ST", "link": "https://www.hemkop.se/produkt/SM\u00d6R-&-RAPS-101244335_ST", "savePrice": "Spara 0,00 kr!"}, {"name": "TANDKR\u00c4M", "price": "24,95 kr/st", "img": "https://d2rfo6yapuixuu.cloudfront.net/h22/hf8/9946332463134/8710908842528_1585442134972_master_axfood_300", "displayVolume": "75ml", "jfr pris": null, "brand": "Zendium", "code": "101264293_ST", "link": "https://www.hemkop.se/produkt/TANDKR\u00c4M-101264293_ST", "savePrice": "Spara 7,45 kr!"}, {"name": "V\u00c5TSERVETTER", "price": "17,95 kr/st", "img": "https://d2rfo6yapuixuu.cloudfront.net/h60/h13/11330105278494/7340083477881_1615219226257_master_axfood_300", "displayVolume": "64st", "jfr pris": null, "brand": "Minstingen"}, {"name": "\u00d6L 2,8%", "price": "21,95 kr/st", "img": "https://d2rfo6yapuixuu.cloudfront.net/h91/h72/11561173254174/7611612501880_1619019337832_master_axfood_300", "displayVolume": "6p/50cl", "jfr pris": null, "brand": "Emd Br\u00e4u", "code": "101294839_ST", "link": "https://www.hemkop.se/produkt/\u00d6L-2,8%-101294839_ST", "savePrice": "Spara 0,00 kr!"}, {"name": "EKO TOFU", "price": "29,95 kr/st", "img": "https://d2rfo6yapuixuu.cloudfront.net/he2/h0a/12104907161630/7332040170546_1632235570961_master_axfood_300", "displayVolume": "400g", "jfr pris": null, "brand": "Yipin", "code": "101271138_ST", "link": "https://www.hemkop.se/produkt/EKO-TOFU-101271138_ST", "savePrice": "Spara 0,00 kr!"}, {"name": "HANDDISK", "price": "16,95 kr/st", "img": "https://d2rfo6yapuixuu.cloudfront.net/h3f/hae/9199850487838/7340083468254_1533991552080_master_axfood_300", "displayVolume": "500ml", "jfr pris": null, "brand": "S\u00e5klart", "code": "101281711_ST", "link": "https://www.hemkop.se/produkt/HANDDISK-101281711_ST", "savePrice": "Spara 0,00 kr!"}, {"name": "EKO SNABBKAFFE", "price": "52,95 kr/st", "img": "https://d2rfo6yapuixuu.cloudfront.net/h03/hce/8857932955678/7340083440076.jpg_master_axfood_300", "displayVolume": "150g", "jfr pris": null, "brand": "Garant Eko", "code": "101230973_ST", "link": "https://www.hemkop.se/produkt/EKO-SNABBKAFFE-101230973_ST", "savePrice": "Spara 0,00 kr!"}, {"name": "EKO KN\u00c4CKEBR\u00d6D", "price": "14,95 kr/st", "img": "https://d2rfo6yapuixuu.cloudfront.net/h72/hd5/9050994343966/07340083460043.jpg_1516581672146_master_axfood_300", "displayVolume": "200g", "jfr pris": null, "brand": "Garant Eko", "code": "101273446_ST", "link": "https://www.hemkop.se/produkt/EKO-KN\u00c4CKEBR\u00d6D-101273446_ST", "savePrice": "Spara 0,00 kr!"}, {"name": "SOJA TAMARI", "price": "39,95 kr/st", "img": "https://d2rfo6yapuixuu.cloudfront.net/hed/hec/9050106200094/07340083455711.jpg_1516379755382_master_axfood_300", "displayVolume": "250ml", "jfr pris": null, "brand": "Garant Eko", "code": "101262873_ST", "link": "https://www.hemkop.se/produkt/SOJA-TAMARI-101262873_ST", "savePrice": "Spara 0,00 kr!"}, {"name": "EKO RAPSOLJA", "price": "44,95 kr/st", "img": "https://d2rfo6yapuixuu.cloudfront.net/h7f/h3c/8861605920798/07340083442919.jpg_master_axfood_300", "displayVolume": "1l", "jfr pris": null, "brand": "Garant Eko", "code": "101231738_ST", "link": "https://www.hemkop.se/produkt/EKO-RAPSOLJA-101231738_ST", "savePrice": "Spara 0,00 kr!"}, {"name": "EKO MAJS", "price": "27,95 kr/st", "img": "https://d2rfo6yapuixuu.cloudfront.net/hbb/h4d/9737329147934/7340083468858_1576707687746_master_axfood_300", "displayVolume": "3x150g", "jfr pris": null, "brand": "Garant Eko", "code": "101286329_ST", "link": "https://www.hemkop.se/produkt/EKO-MAJS-101286329_ST", "savePrice": "Spara 0,00 kr!"}, {"name": "EKO OLIVOLJA ITALIENSK", "price": "54,95 kr/st", "img": "https://d2rfo6yapuixuu.cloudfront.net/h1d/hda/8855321509918/7311041049525.jpg_master_axfood_300", "displayVolume": "500ml", "jfr pris": null, "brand": "Garant Eko", "code": "100917199_ST", "link": "https://www.hemkop.se/produkt/EKO-OLIVOLJA-ITALIENSK-100917199_ST", "savePrice": "Spara 0,00 kr!"}, {"name": "FISKBULLAR", "price": "17,95 kr/st", "img": "https://d2rfo6yapuixuu.cloudfront.net/h1e/hce/11125225848862/7311170041018_1611917732943_master_axfood_300", "displayVolume": "375g", "jfr pris": null, "brand": "Abba", "code": "100442692_ST", "link": "https://www.hemkop.se/produkt/FISKBULLAR-100442692_ST", "savePrice": "Spara 0,00 kr!"}, {"name": "O\u00b4BOY", "price": "26,95 kr/st", "img": "https://d2rfo6yapuixuu.cloudfront.net/h9c/hf1/11013883199518/7622300247942_1610120125188_master_axfood_300", "displayVolume": "700g", "jfr pris": null, "brand": "O'boy", "code": "100906646_ST", "link": "https://www.hemkop.se/produkt/O\u00b4BOY-100906646_ST", "savePrice": "Spara 0,00 kr!"}, {"name": "EKO PESTO", "price": "29,95 kr/st", "img": "https://d2rfo6yapuixuu.cloudfront.net/hb1/h0c/8857861128222/07340083439575.jpg_master_axfood_300", "displayVolume": "190g", "jfr pris": null, "brand": "Garant Eko", "code": "101229969_ST", "link": "https://www.hemkop.se/produkt/EKO-PESTO-101229969_ST", "savePrice": "Spara 0,00 kr!"}, {"name": "EKO SPAGHETTI", "price": "18,95 kr/st", "img": "https://d2rfo6yapuixuu.cloudfront.net/hd8/ha2/9897842933790/7340083478031_1583789755885_master_axfood_300", "displayVolume": "1kg", "jfr pris": null, "brand": "Garant Eko", "code": "101301596_ST", "link": "https://www.hemkop.se/produkt/EKO-SPAGHETTI-101301596_ST", "savePrice": "Spara 0,00 kr!"}, {"name": "START NATURELL", "price": "29,95 kr/st", "img": "https://d2rfo6yapuixuu.cloudfront.net/h75/hae/9217621753886/7310130801709_1535634376240_master_axfood_300", "displayVolume": "750g", "jfr pris": null, "brand": "Start!", "code": "100638035_ST", "link": "https://www.hemkop.se/produkt/START-NATURELL-100638035_ST", "savePrice": "Spara 0,00 kr!"}, {"name": "EKO KOKOSOLJA", "price": "64,95 kr/st", "img": "https://d2rfo6yapuixuu.cloudfront.net/h97/he0/11821744062494/7340083442858_1623967536066_master_axfood_300", "displayVolume": "500ml", "jfr pris": null, "brand": "Garant Eko", "code": "101231432_ST", "link": "https://www.hemkop.se/produkt/EKO-KOKOSOLJA-101231432_ST", "savePrice": "Spara 0,00 kr!"}, {"name": "GAR PARMIGIANO", "price": "59,95 kr/st", "img": "https://d2rfo6yapuixuu.cloudfront.net/hc2/h8e/9822545903646/7340083476860_1580806294987_master_axfood_300", "displayVolume": "200g", "jfr pris": null, "brand": "Garant", "code": "101296557_ST", "link": "https://www.hemkop.se/produkt/GAR-PARMIGIANO-101296557_ST", "savePrice": "Spara 0,00 kr!"}, {"name": "BRIE", "price": "39,95 kr/st", "img": "https://d2rfo6yapuixuu.cloudfront.net/hbb/hd0/8863500828702/07340083440342.jpg_master_axfood_300", "displayVolume": "500g", "jfr pris": null, "brand": "Garant", "code": "101231254_ST", "link": "https://www.hemkop.se/produkt/BRIE-101231254_ST", "savePrice": "Spara 0,00 kr!"}, {"name": "EKO YOGHURT", "price": "15,95 kr/st", "img": "https://d2rfo6yapuixuu.cloudfront.net/h62/hc5/10399291637790/7340083483431_1597352252414_master_axfood_300", "displayVolume": "1kg", "jfr pris": null, "brand": "Garant Eko", "code": "101320609_ST", "link": "https://www.hemkop.se/produkt/EKO-YOGHURT-101320609_ST", "savePrice": "Spara 0,00 kr!"}, {"name": "GAR MJ\u00d6LK", "price": "14,50 kr/st", "img": "https://d2rfo6yapuixuu.cloudfront.net/h2f/h00/8865354645534/07340083435973.jpg_1464164731520_master_axfood_300", "displayVolume": "1l", "jfr pris": null, "brand": "Garant", "code": "101222585_ST", "link": "https://www.hemkop.se/produkt/GAR-MJ\u00d6LK-101222585_ST", "savePrice": "Spara 0,00 kr!"}, {"name": "EKO N\u00d6TF\u00c4RS", "price": "59,95 kr/st", "img": "https://d2rfo6yapuixuu.cloudfront.net/hd3/h6c/9019444854814/07340062471565.jpg_1512411133428_master_axfood_300", "displayVolume": "500g", "jfr pris": null, "brand": "Garant Eko", "code": "101233451_ST", "link": "https://www.hemkop.se/produkt/EKO-N\u00d6TF\u00c4RS-101233451_ST", "savePrice": "Spara 0,00 kr!"}, {"name": "VEGANOST", "price": "49,95 kr/st", "img": "https://d2rfo6yapuixuu.cloudfront.net/h32/h29/12060607053854/5202390007934_1631024743051_master_axfood_300", "displayVolume": "400g", "jfr pris": null, "brand": "Violife", "code": "101257432_ST", "link": "https://www.hemkop.se/produkt/VEGANOST-101257432_ST", "savePrice": "Spara 0,00 kr!"}, {"name": "VEGETARISK PASTEJ", "price": "18,95 kr/st", "img": "https://d2rfo6yapuixuu.cloudfront.net/h9c/h14/9433154027550/7310941801202_1554994830070_master_axfood_300", "displayVolume": "200g", "jfr pris": null, "brand": "Pastejk\u00f6ket", "code": "101261026_ST", "link": "https://www.hemkop.se/produkt/VEGETARISK-PASTEJ-101261026_ST", "savePrice": "Spara 0,00 kr!"}, {"name": "S\u00c5KLART HANDDISKMEDEL", "price": "16,95 kr/st", "img": "https://d2rfo6yapuixuu.cloudfront.net/h27/heb/11821744390174/7340083459122_1623967538748_master_axfood_300", "displayVolume": "0,5l", "jfr pris": null, "brand": "S\u00e5klart", "code": "101261848_ST", "link": "https://www.hemkop.se/produkt/S\u00c5KLART-HANDDISKMEDEL-101261848_ST", "savePrice": "Spara 0,00 kr!"}, {"name": "WCD RENG\u00d6RING", "price": "19,95 kr/st", "img": "https://d2rfo6yapuixuu.cloudfront.net/h84/h19/9382600409118/5000204783452_1551187591583_master_axfood_300", "displayVolume": "750ml", "jfr pris": null, "brand": "Wc Duck", "code": "101226775_ST", "link": "https://www.hemkop.se/produkt/WCD-RENG\u00d6RING-101226775_ST", "savePrice": "Spara 0,00 kr!"}, {"name": "GRUMME S\u00c5PA", "price": "19,95 kr/st", "img": "https://d2rfo6yapuixuu.cloudfront.net/hb4/hdb/9848484691998/7310610021450_1581900012982_master_axfood_300", "displayVolume": "750ml", "jfr pris": null, "brand": "Grumme", "code": "101308699_ST", "link": "https://www.hemkop.se/produkt/GRUMME-S\u00c5PA-101308699_ST", "savePrice": "Spara 0,00 kr!"}, {"name": "RAVIOLI G/FRI", "price": "29,95 kr/st", "img": "https://d2rfo6yapuixuu.cloudfront.net/h0b/h83/8863921897502/07340083447099.jpg_master_axfood_300", "displayVolume": "200g", "jfr pris": null, "brand": "Garant"}, {"name": "PIZZAKIT", "price": "24,95 kr/st", "img": "https://d2rfo6yapuixuu.cloudfront.net/h32/h96/9281239121950/3392590601536_1542275128940_master_axfood_300", "displayVolume": "600g", "jfr pris": null, "brand": "Pop! Bakery", "code": "100093989_ST", "link": "https://www.hemkop.se/produkt/PIZZAKIT-100093989_ST", "savePrice": "Spara 0,00 kr!"}, {"name": "POMMES", "price": "16,95 kr/st", "img": "https://d2rfo6yapuixuu.cloudfront.net/hef/h88/11107526574110/7310240073560_1611678308348_master_axfood_300", "displayVolume": "900g", "jfr pris": null, "brand": "Felix", "code": "100481220_ST", "link": "https://www.hemkop.se/produkt/POMMES-100481220_ST", "savePrice": "Spara 0,00 kr!"}, {"name": "DAZZLEY MIXBOX", "price": "69,95 kr/st", "img": "https://d2rfo6yapuixuu.cloudfront.net/h18/h0f/8920126652446/07311041081068.jpg_1492781486849_master_axfood_300", "displayVolume": "20p", "jfr pris": null, "brand": "Dazzley", "code": "101259136_ST", "link": "https://www.hemkop.se/produkt/DAZZLEY-MIXBOX-101259136_ST", "savePrice": "Spara 0,00 kr!"}, {"name": "KR\u00d6GARPYTT", "price": "36,95 kr/st", "img": "https://d2rfo6yapuixuu.cloudfront.net/h00/h12/11486924603422/7310240075472_1617881188525_master_axfood_300", "displayVolume": "720g", "jfr pris": null, "brand": "Felix", "code": "101231804_ST", "link": "https://www.hemkop.se/produkt/KR\u00d6GARPYTT-101231804_ST", "savePrice": "Spara 0,00 kr!"}, {"name": "FORMBR\u00d6D G/FRI", "price": "28,95 kr/st", "img": "https://d2rfo6yapuixuu.cloudfront.net/hac/he8/9790840733726/7330242200047_1579526432156_master_axfood_300", "displayVolume": "500g", "jfr pris": null, "brand": "Fria", "code": "100677082_ST", "link": "https://www.hemkop.se/produkt/FORMBR\u00d6D-G/FRI-100677082_ST", "savePrice": "Spara 0,00 kr!"}, {"name": "GAR FALUKORV", "price": "28,95 kr/st", "img": "https://d2rfo6yapuixuu.cloudfront.net/h7c/he5/9031827947550/07311041056318.jpg_1513912260110_master_axfood_300", "displayVolume": "800g", "jfr pris": null, "brand": "Garant", "code": "101190071_ST", "link": "https://www.hemkop.se/produkt/GAR-FALUKORV-101190071_ST", "savePrice": "Spara 0,00 kr!"}, {"name": "HOT DOG", "price": "21,95 kr/st", "img": "https://d2rfo6yapuixuu.cloudfront.net/h7e/h73/10832239067166/7300200068002_1606895385960_master_axfood_300", "displayVolume": "500g", "jfr pris": null, "brand": "Scan", "code": "101250877_ST", "link": "https://www.hemkop.se/produkt/HOT-DOG-101250877_ST", "savePrice": "Spara 0,00 kr!"}, {"name": "ELD DUOKAKOR", "price": "9,95 kr/st", "img": "https://d2rfo6yapuixuu.cloudfront.net/h30/h9e/11515362410526/7340083446740_1618495867781_master_axfood_300", "displayVolume": "176g", "jfr pris": null, "brand": "Eldorado", "code": "101243974_ST", "link": "https://www.hemkop.se/produkt/ELD-DUOKAKOR-101243974_ST", "savePrice": "Spara 0,00 kr!"}, {"name": "ELD FORMBR\u00d6D", "price": "13,95 kr/st", "img": "https://d2rfo6yapuixuu.cloudfront.net/h08/h15/10157452328990/7311041012031_1590666015801_master_axfood_300", "displayVolume": "600g", "jfr pris": null, "brand": "Eldorado"}, {"name": "LEKSANDSKN\u00c4CKE", "price": "27,95 kr/st", "img": "https://d2rfo6yapuixuu.cloudfront.net/hcc/he1/12154564378654/7312082001015_1633587070303_master_axfood_300", "displayVolume": "830g", "jfr pris": null, "brand": "Leksands", "code": "100048431_ST", "link": "https://www.hemkop.se/produkt/LEKSANDSKN\u00c4CKE-100048431_ST", "savePrice": "Spara 0,00 kr!"}, {"name": "FINN CRISP", "price": "12,50 kr/st", "img": "https://d2rfo6yapuixuu.cloudfront.net/hf0/hd4/9091141369886/06410500090014.jpg_1521211539194_master_axfood_300", "displayVolume": "200g", "jfr pris": null, "brand": "Finn Crisp", "code": "100167310_ST", "link": "https://www.hemkop.se/produkt/FINN-CRISP-100167310_ST", "savePrice": "Spara 0,00 kr!"}, {"name": "FALU R\u00c5GRUT", "price": "9,95 kr/st", "img": "https://d2rfo6yapuixuu.cloudfront.net/hd5/h71/12023944413214/7300400114783_1630052439489_master_axfood_300", "displayVolume": "235g", "jfr pris": null, "brand": "Wasa", "code": "100738025_ST", "link": "https://www.hemkop.se/produkt/FALU-R\u00c5GRUT-100738025_ST", "savePrice": "Spara 0,00 kr!"}]