[{"name": "Oxfil\u00e9", "img": "https://assets.icanet.se/q_auto,f_auto/c_lpad,h_150,w_150,e_sharpen:70/2373717600008.jpg", "brand": null, "price": "199 kr", "jfr Pris": 199.0}, {"name": "Stekpanna", "img": "https://assets.icanet.se/q_auto,f_auto/c_lpad,h_150,w_150,e_sharpen:70/3168430241343.jpg", "brand": null, "price": "299 kr", "jfr Pris": null}, {"name": "L\u00e4sk", "img": "https://assets.icanet.se/$y_h,$x_w,$pi_current:public_id/c_fit,w_$x,h_$y,u_5449000259240,x_$y_mul_-0.3,y_$x_mul_-0.3/q_auto,f_auto/c_lpad,h_150,w_150,e_sharpen:70/5449000259233.jpg", "brand": null, "price": "79 kr", "jfr Pris": 11.97}, {"name": "Frysta r\u00e4kor med skal 70/90", "img": "https://assets.icanet.se/q_auto,f_auto/c_lpad,h_150,w_150,e_sharpen:70/5740300914328.jpg", "brand": null, "price": "35 kr", "jfr Pris": 70.0}, {"name": "Marschaller", "img": "https://assets.icanet.se/q_auto,f_auto/c_lpad,h_150,w_150,e_sharpen:70/7310380605164.jpg", "brand": null, "price": "15 kr", "jfr Pris": null}, {"name": "Ryggbiff/entrec\u00f4te", "img": "https://assets.icanet.se/q_auto,f_auto/c_lpad,h_150,w_150,e_sharpen:70/2319117200004.jpg", "brand": null, "price": "179 kr", "jfr Pris": 179.0}, {"name": "Prosciutto", "img": "https://assets.icanet.se/q_auto,f_auto/c_lpad,h_150,w_150,e_sharpen:70/7318690101062.jpg", "brand": null, "price": "20 kr", "jfr Pris": 166.67}, {"name": "Lime", "img": "https://assets.icanet.se/q_auto,f_auto/c_lpad,h_150,w_150,e_sharpen:70/2092404800001.jpg", "brand": "", "price": "5 f\u00f6r 10 kr", "jfr Pris": 22.22}, {"name": "Citroner i n\u00e4t", "id": "5002324944", "brand": "ICA. Spanien", "price": "12 kr", "jfr Pris": 25.8, "img": "https://assets.icanet.se/q_auto,f_auto/c_lpad,h_150,w_150,e_sharpen:70/7318690183945.jpg", "displayVolume": "500 g"}, {"name": "Gr\u00f6na k\u00e4rnfria druvor i ask", "id": "5002303324", "brand": "ICA. Sydafrika", "price": "25 kr", "jfr Pris": 50.0, "img": "https://assets.icanet.se/q_auto,f_auto/c_lpad,h_150,w_150,e_sharpen:70/7318693555800.jpg", "displayVolume": "500 g"}, {"name": "Jordgubbar i ask", "id": "5002324949", "brand": "Egypten/Marocko/Spanien", "price": "25 kr", "jfr Pris": 100.0, "img": "https://assets.icanet.se/q_auto,f_auto/c_lpad,h_150,w_150,e_sharpen:70/2092432300009.jpg", "displayVolume": "250 g"}, {"name": "Mogen avokado 3-pack", "id": "5002303307", "brand": "ICA. Colombia/Chile/Mexiko", "price": "25 kr", "jfr Pris": 75.76, "img": "https://assets.icanet.se/q_auto,f_auto/c_lpad,h_150,w_150,e_sharpen:70/7318690158394.jpg", "displayVolume": "330 g"}, {"name": "Piel de sapo melon", "id": "5002303319", "brand": "Brasilien/Costa Rica", "price": "20 kr", "jfr Pris": 20.0, "img": "https://assets.icanet.se/q_auto,f_auto/c_lpad,h_150,w_150,e_sharpen:70/2092310100004.jpg"}, {"name": "Svartk\u00e5l i p\u00e5se", "id": "5002303310", "brand": "ICA. Spanien", "price": "20 kr", "jfr Pris": 100.0, "img": "https://assets.icanet.se/q_auto,f_auto/c_lpad,h_150,w_150,e_sharpen:70/7318690157601.jpg", "displayVolume": "200 g"}, {"name": "\u00c4pplen Jazz", "id": "5002303285", "brand": "ICA Selection. Italien/Frankrike", "price": "29 kr", "jfr Pris": 29.9, "img": "https://assets.icanet.se/q_auto,f_auto/c_lpad,h_150,w_150,e_sharpen:70/2092329300006.jpg"}, {"name": "Digestive", "id": "5002303299", "brand": "McVities", "price": "25 kr", "jfr Pris": 41.67, "img": "https://assets.icanet.se/$y_h,$x_w,$pi_current:public_id/c_fit,w_$x,h_$y,u_5000396026993,x_$y_mul_-0.3,y_$x_mul_-0.3/q_auto,f_auto/c_lpad,h_150,w_150,e_sharpen:70/5000396026993.jpg", "displayVolume": "300-400 g"}, {"name": "Kex", "id": "5002303371", "brand": "TUC", "price": "20 kr", "jfr Pris": 66.67, "img": "https://assets.icanet.se/$y_h,$x_w,$pi_current:public_id/c_fit,w_$x,h_$y,u_5410041001204,x_$y_mul_-0.3,y_$x_mul_-0.3/c_fit,w_$x,h_$y,u_5410041066005,x_$y_mul_-0.3,y_$x_mul_0.6,g_south_east/q_auto,f_auto/c_lpad,h_150,w_150,e_sharpen:70/5410041332209.jpg", "displayVolume": "100 g"}, {"name": "Korv-,Hamburgerbr\u00f6d Potato", "id": "5002303311", "brand": "Korvbr\u00f6dsbagarn", "price": "40 kr", "jfr Pris": 74.07, "img": "https://assets.icanet.se/$y_h,$x_w,$pi_current:public_id/c_fit,w_$x,h_$y,u_7311372167004,x_$y_mul_-0.3,y_$x_mul_-0.3/q_auto,f_auto/c_lpad,h_150,w_150,e_sharpen:70/7311372147730.jpg", "displayVolume": "270-280 g"}, {"name": "Roast\u00b4n toast, Energi", "id": "5002318604", "brand": "P\u00e5gen", "price": "22 kr", "jfr Pris": 32.71, "img": "https://assets.icanet.se/$y_h,$x_w,$pi_current:public_id/c_fit,w_$x,h_$y,u_7311070336160,x_$y_mul_-0.3,y_$x_mul_-0.3/q_auto,f_auto/c_lpad,h_150,w_150,e_sharpen:70/7311070330090.jpg", "displayVolume": "700-800 g"}, {"name": "Bacon", "id": "5002303330", "brand": "Scan", "price": "25 kr", "jfr Pris": 89.29, "img": "https://assets.icanet.se/$y_h,$x_w,$pi_current:public_id/c_fit,w_$x,h_$y,u_7300208345006,x_$y_mul_-0.3,y_$x_mul_0.6,g_south_east/q_auto,f_auto/c_lpad,h_150,w_150,e_sharpen:70/7300208345006.jpg", "displayVolume": "140 g"}, {"name": "Dessertost", "id": "5002303327", "brand": "Castello", "price": "35 kr", "jfr Pris": 175.0, "img": "https://assets.icanet.se/$y_h,$x_w,$pi_current:public_id/c_fit,w_$x,h_$y,u_5740200001012,x_$y_mul_-0.3,y_$x_mul_0.6,g_south_east/q_auto,f_auto/c_lpad,h_150,w_150,e_sharpen:70/5740200017013.jpg", "displayVolume": "100-150 g"}, {"name": "Ekologisk ryggbiff", "id": "5002303316", "brand": "ICA I Love Eco. Ursprung Sverige", "price": "259 kr", "jfr Pris": 259.0, "img": "https://assets.icanet.se/q_auto,f_auto/c_lpad,h_150,w_150,e_sharpen:70/2319136600007.jpg", "displayVolume": "Ca 300 g"}, {"name": "F\u00e4rsk kycklingfil\u00e9", "id": "5002324947", "brand": "Kronf\u00e5gel. Ursprung Sverige", "price": "99 kr", "jfr Pris": 99.0, "img": "https://assets.icanet.se/q_auto,f_auto/c_lpad,h_150,w_150,e_sharpen:70/2332804000008.jpg", "displayVolume": "Ca 700-925 g"}, {"name": "F\u00e4rsk Pizza", "id": "5002303302", "brand": "ICA", "price": "35 kr", "jfr Pris": 75.27, "img": "https://assets.icanet.se/$y_h,$x_w,$pi_current:public_id/c_fit,w_$x,h_$y,u_7318690159711,x_$y_mul_-0.3,y_$x_mul_-0.3/q_auto,f_auto/c_lpad,h_150,w_150,e_sharpen:70/7318690144618.jpg", "displayVolume": "465-520 g"}, {"name": "F\u00e4rskost", "id": "5002303339", "brand": "Philadelphia", "price": "30 kr", "jfr Pris": 100.0, "img": "https://assets.icanet.se/$y_h,$x_w,$pi_current:public_id/c_fit,w_$x,h_$y,u_4000339697908,x_$y_mul_-0.3,y_$x_mul_0.6,g_south_east/q_auto,f_auto/c_lpad,h_150,w_150,e_sharpen:70/7622201777197.jpg", "displayVolume": "150-200 g"}, {"name": "Hummer", "id": "5002303329", "brand": "ICA", "price": "179 kr", "jfr Pris": 421.18, "img": "https://assets.icanet.se/q_auto,f_auto/c_lpad,h_150,w_150,e_sharpen:70/7318690498186.jpg", "displayVolume": "425 g"}, {"name": "H\u00e4ngm\u00f6rad oxfil\u00e9", "id": "5002303340", "brand": "Highland Beef. Ursprung Skottland", "price": "359 kr", "jfr Pris": 359.0, "img": "https://assets.icanet.se/q_auto,f_auto/c_lpad,h_150,w_150,e_sharpen:70/2357205900009.jpg", "displayVolume": "Ca 800 g"}, {"name": "Kalkonbr\u00f6stfil\u00e9, tunnskivad kalkonfil\u00e9", "id": "5002303388", "brand": "Ingelsta kalkon. Ursprung Sverige", "price": "149 kr", "jfr Pris": 149.0, "img": "https://assets.icanet.se/q_auto,f_auto/c_lpad,h_150,w_150,e_sharpen:70/2366056000004.jpg", "displayVolume": "Ca 450-480 g"}, {"name": "Kyld s\u00e5s, dressing", "id": "5002303323", "brand": "Eriks", "price": "35 kr", "jfr Pris": 102.94, "img": "https://assets.icanet.se/$y_h,$x_w,$pi_current:public_id/c_fit,w_$x,h_$y,u_7350042720002,x_$y_mul_-0.3,y_$x_mul_0.6,g_south_east/q_auto,f_auto/c_lpad,h_150,w_150,e_sharpen:70/7350042722372.jpg", "displayVolume": "170-255 ml"}, {"name": "Lammracks", "id": "5002303385", "brand": "Ursprung Nya Zeeland", "price": "299 kr", "jfr Pris": 299.0, "img": "https://assets.icanet.se/q_auto,f_auto/c_lpad,h_150,w_150,e_sharpen:70/2373719000004.jpg", "displayVolume": "Ca 800 g"}, {"name": "Marina r\u00f6ror", "id": "5002303320", "brand": "Rydbergs", "price": "29 kr", "jfr Pris": 74.75, "img": "https://assets.icanet.se/q_auto,f_auto/c_lpad,h_150,w_150,e_sharpen:70/7313160005024.jpg", "displayVolume": "400 g"}, {"name": "Potatisgrat\u00e4ng, rotfruktsgrat\u00e4ng", "id": "5002303360", "brand": "Peka", "price": "45 kr", "jfr Pris": 22.5, "img": "https://assets.icanet.se/$y_h,$x_w,$pi_current:public_id/c_fit,w_$x,h_$y,u_8711118016020,x_$y_mul_-0.3,y_$x_mul_0.6,g_south_east/q_auto,f_auto/c_lpad,h_150,w_150,e_sharpen:70/8711118019816.jpg", "displayVolume": "2000 g"}, {"name": "Pr\u00e4st\u00ae, Herrg\u00e5rd\u00ae, Grev\u00e9\u00ae, Svecia", "id": "5002303322", "brand": "Arla", "price": "99 kr", "jfr Pris": 99.0, "img": "https://assets.icanet.se/$y_h,$x_w,$pi_current:public_id/c_fit,w_$x,h_$y,u_2340385800009,x_$y_mul_-0.3,y_$x_mul_-0.3/c_fit,w_$x,h_$y,u_2340386300003,x_$y_mul_-0.3,y_$x_mul_0.6,g_south_east/q_auto,f_auto/c_lpad,h_150,w_150,e_sharpen:70/2340386100009.jpg", "displayVolume": "ca 500-690 g"}, {"name": "Renytterfil\u00e9", "id": "5002303301", "brand": "Norrlandsvilt. Ursprung Sverige", "price": "399 kr", "jfr Pris": 399.0, "img": "https://assets.icanet.se/q_auto,f_auto/c_lpad,h_150,w_150,e_sharpen:70/2356265200005.jpg", "displayVolume": "Ca 600 g"}, {"name": "\u00d6lkorv", "id": "5002303284", "brand": "Ridderheims", "price": "25 kr", "jfr Pris": 250.0, "img": "https://assets.icanet.se/$y_h,$x_w,$pi_current:public_id/c_fit,w_$x,h_$y,u_7392555502041,x_$y_mul_-0.3,y_$x_mul_0.6,g_south_east/q_auto,f_auto/c_lpad,h_150,w_150,e_sharpen:70/7392555502089.jpg", "displayVolume": "50 g"}, {"name": "Alkoholfritt mousserande vin", "id": "5002324948", "brand": "Campo Viejo", "price": "69 kr", "jfr Pris": 92.0, "img": "https://assets.icanet.se/q_auto,f_auto/c_lpad,h_150,w_150,e_sharpen:70/8410302983352.jpg", "displayVolume": "750 ml"}, {"name": "Chips, Ostb\u00e5gar", "id": "5002303331", "brand": "OLW", "price": "45 kr", "jfr Pris": 100.0, "img": "https://assets.icanet.se/$y_h,$x_w,$pi_current:public_id/c_fit,w_$x,h_$y,u_7340005403332,x_$y_mul_-0.3,y_$x_mul_-0.3/c_fit,w_$x,h_$y,u_7340005403554,x_$y_mul_-0.3,y_$x_mul_0.6,g_south_east/q_auto,f_auto/c_lpad,h_150,w_150,e_sharpen:70/7340005406043.jpg", "displayVolume": "150, 200-275 g"}, {"name": "Chokladkaka premium", "id": "5002303300", "brand": "Marabou", "price": "30 kr", "jfr Pris": 150.0, "img": "https://assets.icanet.se/$y_h,$x_w,$pi_current:public_id/c_fit,w_$x,h_$y,u_7622300544010,x_$y_mul_-0.3,y_$x_mul_0.6,g_south_east/q_auto,f_auto/c_lpad,h_150,w_150,e_sharpen:70/7622400624520.jpg", "displayVolume": "100 g"}, {"name": "Cider", "id": "5002303332", "brand": "Kopparbergs", "price": "19 kr", "jfr Pris": 15.08, "img": "https://assets.icanet.se/$y_h,$x_w,$pi_current:public_id/c_fit,w_$x,h_$y,u_7393714312440,x_$y_mul_-0.3,y_$x_mul_0.6,g_south_east/q_auto,f_auto/c_lpad,h_150,w_150,e_sharpen:70/7393714312648.jpg", "displayVolume": "4 x 330 ml"}, {"name": "Dubbla stycksaker", "id": "5002303321", "brand": "Marabou", "price": "15 kr", "jfr Pris": 135.14, "img": "https://assets.icanet.se/$y_h,$x_w,$pi_current:public_id/c_fit,w_$x,h_$y,u_7040110663200,x_$y_mul_-0.3,y_$x_mul_-0.3/c_fit,w_$x,h_$y,u_7310511257507,x_$y_mul_-0.3,y_$x_mul_0.6,g_south_east/q_auto,f_auto/c_lpad,h_150,w_150,e_sharpen:70/7622210865335.jpg", "displayVolume": "37-60 g"}, {"name": "Fond", "id": "5002303296", "brand": "Touch of Taste", "price": "24 kr", "jfr Pris": 6.22, "img": "https://assets.icanet.se/q_auto,f_auto/c_lpad,h_150,w_150,e_sharpen:70/7322550052739.jpg", "displayVolume": "180 ml"}, {"name": "Grekiska Oliver", "id": "5002303382", "brand": "Zeta", "price": "45 kr", "jfr Pris": 132.35, "img": "https://assets.icanet.se/$y_h,$x_w,$pi_current:public_id/c_fit,w_$x,h_$y,u_7350002404874,x_$y_mul_-0.3,y_$x_mul_0.6,g_south_east/q_auto,f_auto/c_lpad,h_150,w_150,e_sharpen:70/7350002405550.jpg", "displayVolume": "370 g"}, {"name": "Kaffe hela b\u00f6nor", "id": "5002303351", "brand": "Zoegas", "price": "52 kr", "jfr Pris": 117.56, "img": "https://assets.icanet.se/q_auto,f_auto/c_lpad,h_150,w_150,e_sharpen:70/7310731101802.jpg", "displayVolume": "450 g"}, {"name": "Kryddor i sm\u00e5 Glas", "id": "5002324945", "brand": "Santa Maria", "price": "30 kr", "jfr Pris": 5000.0, "img": "https://assets.icanet.se/$y_h,$x_w,$pi_current:public_id/c_fit,w_$x,h_$y,u_7311311014536,x_$y_mul_-0.3,y_$x_mul_0.6,g_south_east/q_auto,f_auto/c_lpad,h_150,w_150,e_sharpen:70/7311311014574.jpg", "displayVolume": "3-80 g"}, {"name": "L\u00e4sk", "id": "5002303356", "brand": "Pepsi, Zingo, 7-up", "price": "36 kr", "jfr Pris": 8.0, "img": "https://assets.icanet.se/$y_h,$x_w,$pi_current:public_id/c_fit,w_$x,h_$y,u_7310070004680,x_$y_mul_-0.3,y_$x_mul_-0.3/c_fit,w_$x,h_$y,u_7310070378507,x_$y_mul_-0.3,y_$x_mul_0.6,g_south_east/q_auto,f_auto/c_lpad,h_150,w_150,e_sharpen:70/7310070382306.jpg", "displayVolume": "1,5 liter"}, {"name": "L\u00e4sk", "id": "5002303386", "brand": "Schweppes", "price": "30 kr", "jfr Pris": 10.0, "img": "https://assets.icanet.se/$y_h,$x_w,$pi_current:public_id/c_fit,w_$x,h_$y,u_7310401003245,x_$y_mul_-0.3,y_$x_mul_-0.3/c_fit,w_$x,h_$y,u_7310401003306,x_$y_mul_-0.3,y_$x_mul_0.6,g_south_east/q_auto,f_auto/c_lpad,h_150,w_150,e_sharpen:70/7310401043203.jpg", "displayVolume": "150 cl"}, {"name": "Majonn\u00e4s", "id": "5002303357", "brand": "Hellmanns", "price": "23 kr", "jfr Pris": 59.75, "img": "https://assets.icanet.se/q_auto,f_auto/c_lpad,h_150,w_150,e_sharpen:70/5000184321064.jpg", "displayVolume": "400 g"}, {"name": "Mineralvatten", "id": "5002343235", "brand": "Raml\u00f6sa", "price": "24 kr", "jfr Pris": 5.33, "img": "https://assets.icanet.se/$y_h,$x_w,$pi_current:public_id/c_fit,w_$x,h_$y,u_7310070001832,x_$y_mul_-0.3,y_$x_mul_-0.3/c_fit,w_$x,h_$y,u_7310070001849,x_$y_mul_-0.3,y_$x_mul_0.6,g_south_east/q_auto,f_auto/c_lpad,h_150,w_150,e_sharpen:70/7310070001900.jpg", "displayVolume": "150 cl"}, {"name": "Moppset", "id": "5002303368", "brand": null, "price": "259 kr", "jfr Pris": 153.93, "img": "https://assets.icanet.se/q_auto,f_auto/c_lpad,h_150,w_150,e_sharpen:70/4023103168275.jpg"}, {"name": "N\u00f6tmix", "id": "5002324946", "brand": "OLW", "price": "15 kr", "jfr Pris": 75.0, "img": "https://assets.icanet.se/q_auto,f_auto/c_lpad,h_150,w_150,e_sharpen:70/7340005403462.jpg", "displayVolume": "200 g"}, {"name": "Tag 3 TexMex betala f\u00f6r 2", "id": "5002303359", "brand": "Santa Maria", "price": "K&#246;p 3 betala f&#246;r 2 kr", "jfr Pris": null, "img": "https://assets.icanet.se/$y_h,$x_w,$pi_current:public_id/c_fit,w_$x,h_$y,u_7311310031015,x_$y_mul_-0.3,y_$x_mul_-0.3/c_fit,w_$x,h_$y,u_7311311020599,x_$y_mul_-0.3,y_$x_mul_0.6,g_south_east/q_auto,f_auto/c_lpad,h_150,w_150,e_sharpen:70/7311312002112.jpg", "displayVolume": "15-742 g"}, {"name": "Flytande margarin", "id": "5002303308", "brand": "Milda Culinesse", "price": "20 kr", "jfr Pris": 26.67, "img": "https://assets.icanet.se/q_auto,f_auto/c_lpad,h_150,w_150,e_sharpen:70/8719200007772.jpg", "displayVolume": "750 ml"}, {"name": "Fruktdryck", "id": "5002303337", "brand": "Proviva", "price": "40 kr", "jfr Pris": 20.0, "img": "https://assets.icanet.se/$y_h,$x_w,$pi_current:public_id/c_fit,w_$x,h_$y,u_7350000550535,x_$y_mul_-0.3,y_$x_mul_0.6,g_south_east/q_auto,f_auto/c_lpad,h_150,w_150,e_sharpen:70/7350000550573.jpg", "displayVolume": "1 liter"}, {"name": "Matlagnings-, vispgr\u00e4dde", "id": "5002303313", "brand": "Sk\u00e5nemejerier", "price": "38 kr", "jfr Pris": 38.0, "img": "https://assets.icanet.se/$y_h,$x_w,$pi_current:public_id/c_fit,w_$x,h_$y,u_7310867523301,x_$y_mul_-0.3,y_$x_mul_0.6,g_south_east/q_auto,f_auto/c_lpad,h_150,w_150,e_sharpen:70/7310867523608.jpg", "displayVolume": "5 dl"}, {"name": "Smoothie", "id": "5002303312", "brand": "Bravo", "price": "20 kr", "jfr Pris": 20.0, "img": "https://assets.icanet.se/q_auto,f_auto/c_lpad,h_150,w_150,e_sharpen:70/7310867565905.jpg", "displayVolume": "1 liter"}, {"name": "Yoghurt smoothie", "id": "5002350105", "brand": "Sk\u00e5nemejerier", "price": "17 kr", "jfr Pris": 17.9, "img": "https://assets.icanet.se/q_auto,f_auto/c_lpad,h_150,w_150,e_sharpen:70/7310867535403.jpg", "displayVolume": "1 kg"}, {"name": "Br\u00e4nnare", "id": "5002350175", "brand": "Flame Boy", "price": "199 kr", "jfr Pris": null, "img": "https://assets.icanet.se/q_auto,f_auto/c_lpad,h_150,w_150,e_sharpen:70/4713431004047.jpg"}, {"name": "Doseringstratt", "id": "5002350083", "brand": null, "price": "59 kr", "jfr Pris": null, "img": "https://assets.icanet.se/q_auto,f_auto/c_lpad,h_150,w_150,e_sharpen:70/7314994210103.jpg"}, {"name": "Elvisp", "id": "5002350174", "brand": "Bosch MFQ3010", "price": "199 kr", "jfr Pris": null, "img": "https://assets.icanet.se/q_auto,f_auto/c_lpad,h_150,w_150,e_sharpen:70/4242002439808.jpg"}, {"name": "Konserveringsglas", "id": "5002350151", "brand": null, "price": "20 kr", "jfr Pris": null, "img": "https://assets.icanet.se/q_auto,f_auto/c_lpad,h_150,w_150,e_sharpen:70/8004360070132.jpg"}, {"name": "Kronljus", "id": "5002342611", "brand": "ICA", "price": "K&#246;p 4 betala f&#246;r 3 kr", "jfr Pris": null, "img": "https://assets.icanet.se/q_auto,f_auto/c_lpad,h_150,w_150,e_sharpen:70/7331210136085.jpg"}, {"name": "Kronljus", "id": "5002350152", "brand": "ICA", "price": "99 kr", "jfr Pris": 3.3, "img": "", "displayVolume": "30-pack"}, {"name": "Kronljus", "id": "5002303348", "brand": "ICA", "price": "99 kr", "jfr Pris": null, "img": "https://assets.icanet.se/q_auto,f_auto/c_lpad,h_150,w_150,e_sharpen:70/7310380423096.jpg", "displayVolume": "30-pack"}, {"name": "Maskindiskmedel", "id": "5002303364", "brand": "Finish", "price": "59 kr", "jfr Pris": 1.48, "img": "https://assets.icanet.se/$y_h,$x_w,$pi_current:public_id/c_fit,w_$x,h_$y,u_5701092114211,x_$y_mul_-0.3,y_$x_mul_-0.3/c_fit,w_$x,h_$y,u_5701092112101,x_$y_mul_-0.3,y_$x_mul_0.6,g_south_east/q_auto,f_auto/c_lpad,h_150,w_150,e_sharpen:70/5701092110404.jpg", "displayVolume": "40-48 pack, 900 ml"}, {"name": "Ny\u00e5rsarrangemang", "id": "5002303369", "brand": null, "price": "129 kr", "jfr Pris": 129.0, "img": "https://assets.icanet.se/q_auto,f_auto/c_lpad,h_150,w_150,e_sharpen:70/8719956284076.jpg"}, {"name": "Ny\u00e5rsbukett", "id": "5002303370", "brand": null, "price": "99 kr", "jfr Pris": null, "img": "https://assets.icanet.se/q_auto,f_auto/c_lpad,h_150,w_150,e_sharpen:70/7318690488187.jpg"}, {"name": "Orkid\u00e9", "id": "5002350104", "brand": "ICA", "price": "89 kr", "jfr Pris": null, "img": "https://assets.icanet.se/q_auto,f_auto/c_lpad,h_150,w_150,e_sharpen:70/7318690492016.jpg"}, {"name": "PET-flaska 3-pack", "id": "5002350145", "brand": "Sodastream", "price": "99 kr", "jfr Pris": null, "img": "https://assets.icanet.se/q_auto,f_auto/c_lpad,h_150,w_150,e_sharpen:70/8718309253783.jpg"}, {"name": "Planksteksbr\u00e4da 2-pack", "id": "5002350108", "brand": "ICA", "price": "199 kr", "jfr Pris": null, "img": "https://assets.icanet.se/q_auto,f_auto/c_lpad,h_150,w_150,e_sharpen:70/7314992550928.jpg"}, {"name": "Ramekin", "id": "5002303367", "brand": "ICA", "price": "15 kr", "jfr Pris": null, "img": "https://assets.icanet.se/q_auto,f_auto/c_lpad,h_150,w_150,e_sharpen:70/7310380525950.jpg"}, {"name": "Rosor 9-pack R\u00f6da Korset", "id": "5002350146", "brand": "ICA. Fairtrade", "price": "59 kr", "jfr Pris": null, "img": "https://assets.icanet.se/q_auto,f_auto/c_lpad,h_150,w_150,e_sharpen:70/7318690488590.jpg"}, {"name": "Spritsp\u00e5se", "id": "5002303353", "brand": null, "price": "39 kr", "jfr Pris": null, "img": "https://assets.icanet.se/q_auto,f_auto/c_lpad,h_150,w_150,e_sharpen:70/7314990222131.jpg"}, {"name": "Tv\u00e4ttmedel, Sk\u00f6ljmedel", "id": "5002350106", "brand": "Via, Comfort", "price": "99 kr", "jfr Pris": 38.28, "img": "https://assets.icanet.se/$y_h,$x_w,$pi_current:public_id/c_fit,w_$x,h_$y,u_8710847999048,x_$y_mul_-0.3,y_$x_mul_-0.3/c_fit,w_$x,h_$y,u_8710847999024,x_$y_mul_-0.3,y_$x_mul_0.6,g_south_east/q_auto,f_auto/c_lpad,h_150,w_150,e_sharpen:70/8720181127809.jpg"}, {"name": "T\u00e4ndkuber", "id": "5002303350", "brand": "Fire Up", "price": "34 kr", "jfr Pris": null, "img": "https://assets.icanet.se/q_auto,f_auto/c_lpad,h_150,w_150,e_sharpen:70/7392754070280.jpg", "displayVolume": "100-pack"}, {"name": "H\u00e5rstyling, torrschampo", "id": "5002345986", "brand": "ICA", "price": "20 kr", "jfr Pris": 100.0, "img": "https://assets.icanet.se/$y_h,$x_w,$pi_current:public_id/c_fit,w_$x,h_$y,u_7318690113485,x_$y_mul_-0.3,y_$x_mul_-0.3/c_fit,w_$x,h_$y,u_7318690125440,x_$y_mul_-0.3,y_$x_mul_0.6,g_south_east/q_auto,f_auto/c_lpad,h_150,w_150,e_sharpen:70/7318690161271.jpg", "displayVolume": "200 ml"}, {"name": "Lash sensational mascara", "id": "5002303349", "brand": "Maybelline", "price": "109 kr", "jfr Pris": null, "img": "https://assets.icanet.se/$y_h,$x_w,$pi_current:public_id/c_fit,w_$x,h_$y,u_3600531143459,x_$y_mul_-0.3,y_$x_mul_-0.3/c_fit,w_$x,h_$y,u_3600531143657,x_$y_mul_-0.3,y_$x_mul_0.6,g_south_east/q_auto,f_auto/c_lpad,h_150,w_150,e_sharpen:70/3600531230906.jpg"}, {"name": "Schampo, balsam, inpackning", "id": "5002345984", "brand": "Aussie", "price": "100 kr", "jfr Pris": 500.0, "img": "https://assets.icanet.se/$y_h,$x_w,$pi_current:public_id/c_fit,w_$x,h_$y,u_4084500618114,x_$y_mul_-0.3,y_$x_mul_-0.3/c_fit,w_$x,h_$y,u_5410076390809,x_$y_mul_-0.3,y_$x_mul_0.6,g_south_east/q_auto,f_auto/c_lpad,h_150,w_150,e_sharpen:70/5410076390830.jpg", "displayVolume": "100-300 ml"}, {"name": "Superstay matte ink", "id": "5002303344", "brand": "Maybelline", "price": "89 kr", "jfr Pris": 0.0, "img": "https://assets.icanet.se/$y_h,$x_w,$pi_current:public_id/c_fit,w_$x,h_$y,u_3600531411107,x_$y_mul_-0.3,y_$x_mul_-0.3/c_fit,w_$x,h_$y,u_3600531411114,x_$y_mul_-0.3,y_$x_mul_0.6,g_south_east/q_auto,f_auto/c_lpad,h_150,w_150,e_sharpen:70/3600531469498.jpg"}, {"name": "Tandkr\u00e4m, tandborste", "id": "5002345978", "brand": "Colgate", "price": "30 kr", "jfr Pris": 15.0, "img": "https://assets.icanet.se/$y_h,$x_w,$pi_current:public_id/c_fit,w_$x,h_$y,u_8714789417066,x_$y_mul_-0.3,y_$x_mul_-0.3/c_fit,w_$x,h_$y,u_8718951179769,x_$y_mul_-0.3,y_$x_mul_0.6,g_south_east/q_auto,f_auto/c_lpad,h_150,w_150,e_sharpen:70/8718951265806.jpg", "displayVolume": "50 ml, 125 ml, 1-pack"}, {"name": "True match foundation", "id": "5002346001", "brand": "L&#180;or\u00e9al Paris", "price": "129 kr", "jfr Pris": 0.0, "img": "https://assets.icanet.se/$y_h,$x_w,$pi_current:public_id/c_fit,w_$x,h_$y,u_3600522862390,x_$y_mul_-0.3,y_$x_mul_0.6,g_south_east/q_auto,f_auto/c_lpad,h_150,w_150,e_sharpen:70/3600522862482.jpg"}, {"name": "Volume lash styler,Grand volume lash styler, Grand volume lash curler mascara", "id": "5002303333", "brand": "IsaDora", "price": "99 kr", "jfr Pris": null, "img": "https://assets.icanet.se/$y_h,$x_w,$pi_current:public_id/c_fit,w_$x,h_$y,u_7317851231303,x_$y_mul_-0.3,y_$x_mul_-0.3/c_fit,w_$x,h_$y,u_7317851231402,x_$y_mul_-0.3,y_$x_mul_0.6,g_south_east/q_auto,f_auto/c_lpad,h_150,w_150,e_sharpen:70/7317851231600.jpg"}, {"name": "Fryst pizza Rustica", "id": "5002303334", "brand": "Dr Oetker", "price": "100 kr", "jfr Pris": 61.73, "img": "https://assets.icanet.se/$y_h,$x_w,$pi_current:public_id/c_fit,w_$x,h_$y,u_4001724010753,x_$y_mul_-0.3,y_$x_mul_-0.3/c_fit,w_$x,h_$y,u_4001724010784,x_$y_mul_-0.3,y_$x_mul_0.6,g_south_east/q_auto,f_auto/c_lpad,h_150,w_150,e_sharpen:70/4001724032601.jpg", "displayVolume": "540-610 g"}, {"name": "Fryst potatis", "id": "5002303383", "brand": "Lamb weston", "price": "35 kr", "jfr Pris": 29.17, "img": "https://assets.icanet.se/$y_h,$x_w,$pi_current:public_id/c_fit,w_$x,h_$y,u_8711571012119,x_$y_mul_-0.3,y_$x_mul_0.6,g_south_east/q_auto,f_auto/c_lpad,h_150,w_150,e_sharpen:70/8711571053402.jpg", "displayVolume": "600-750 g"}, {"name": "Fryst t\u00e5rta", "id": "5002303354", "brand": "Fr\u00f6dinge", "price": "39 kr", "jfr Pris": 99.75, "img": "https://assets.icanet.se/q_auto,f_auto/c_lpad,h_150,w_150,e_sharpen:70/7310890601601.jpg", "displayVolume": "400-500 g"}, {"name": "Frysta vegonuggets", "id": "5002303352", "brand": "ICA", "price": "29 kr", "jfr Pris": 99.67, "img": "https://assets.icanet.se/q_auto,f_auto/c_lpad,h_150,w_150,e_sharpen:70/7318690174561.jpg", "displayVolume": "300 g"}, {"name": "Frysta \u00e4rtor, brysselk\u00e5l", "id": "5002303358", "brand": "ICA", "price": "22 kr", "jfr Pris": 20.0, "img": "https://assets.icanet.se/$y_h,$x_w,$pi_current:public_id/c_fit,w_$x,h_$y,u_7318690010425,x_$y_mul_-0.3,y_$x_mul_0.6,g_south_east/q_auto,f_auto/c_lpad,h_150,w_150,e_sharpen:70/7318690057147.jpg", "displayVolume": "550-600 g"}, {"name": "Glass ekologisk, laktosfri", "id": "5002303342", "brand": "SIA Glass", "price": "29 kr", "jfr Pris": 39.87, "img": "https://assets.icanet.se/q_auto,f_auto/c_lpad,h_150,w_150,e_sharpen:70/7312690306038.jpg", "displayVolume": "750 ml"}, {"name": "Glass", "id": "5002350086", "brand": "SIA Glass", "price": "29 kr", "jfr Pris": 19.93, "img": "https://assets.icanet.se/q_auto,f_auto/c_lpad,h_150,w_150,e_sharpen:70/7312690021405.jpg", "displayVolume": "1,5 liter"}, {"name": "2000 calorie mascara", "id": "5002350131", "brand": "Max Factor", "price": "99 kr", "jfr Pris": null, "img": "https://assets.icanet.se/q_auto,f_auto/c_lpad,h_150,w_150,e_sharpen:70/DR_5002346002.jpg"}, {"name": "Antikljus tvist", "id": "5002350125", "brand": "ICA", "price": "49 kr", "jfr Pris": null, "img": "https://assets.icanet.se/$y_h,$x_w,$pi_current:public_id/c_fit,w_$x,h_$y,u_7313136019321,x_$y_mul_-0.3,y_$x_mul_-0.3/q_auto,f_auto/c_lpad,h_150,w_150,e_sharpen:70/7313136019314.jpg", "displayVolume": "2-pack"}, {"name": "Eng\u00e5ngsglas/tallrikar", "id": "5002303347", "brand": "ICA", "price": "25% kr", "jfr Pris": null, "img": "https://assets.icanet.se/$y_h,$x_w,$pi_current:public_id/c_fit,w_$x,h_$y,u_7313136028149,x_$y_mul_-0.3,y_$x_mul_-0.3/c_fit,w_$x,h_$y,u_7313136028361,x_$y_mul_-0.3,y_$x_mul_0.6,g_south_east/q_auto,f_auto/c_lpad,h_150,w_150,e_sharpen:70/7313136028293.jpg"}, {"name": "Flytande tv\u00e5l", "id": "5002350109", "brand": "300 ml", "price": "15 kr", "jfr Pris": 50.0, "img": "https://assets.icanet.se/$y_h,$x_w,$pi_current:public_id/c_fit,w_$x,h_$y,u_7318690489870,x_$y_mul_-0.3,y_$x_mul_0.6,g_south_east/q_auto,f_auto/c_lpad,h_150,w_150,e_sharpen:70/7318690489887.jpg", "displayVolume": "ICA"}, {"name": "Kolsyremaskin", "id": "5002342604", "brand": "Sodastream", "price": "699 kr", "jfr Pris": null, "img": "https://assets.icanet.se/q_auto,f_auto/c_lpad,h_150,w_150,e_sharpen:70/8719128115283.jpg"}, {"name": "Mixa och Matcha", "id": "5002350128", "brand": "ICA I love eco", "price": "179 kr", "jfr Pris": 89.5, "img": "", "displayVolume": "Stl xs-xl"}, {"name": "Sugr\u00f6r", "id": "bottom-bar", "brand": null, "price": "29 kr", "jfr Pris": null, "img": "https://assets.icanet.se/q_auto,f_auto/c_lpad,h_150,w_150,e_sharpen:70/7393885214970.jpg", "displayVolume": "10-pack"}]