[{"name": "Bregott", "img": "https://assets.icanet.se/$y_h,$x_w,$pi_current:public_id/c_fit,w_$x,h_$y,u_7310860005804,x_$y_mul_-0.3,y_$x_mul_-0.3/q_auto,f_auto/c_lpad,h_150,w_150,e_sharpen:70/7310860005767.jpg", "brand": null, "price": "25 kr", "jfr Pris": 41.67}, {"name": "Pizzakit", "img": "https://assets.icanet.se/q_auto,f_auto/c_lpad,h_150,w_150,e_sharpen:70/7318690166726.jpg", "brand": null, "price": "10 kr", "jfr Pris": 16.67}, {"name": "Fryst laxfil\u00e9", "img": "https://assets.icanet.se/q_auto,f_auto/c_lpad,h_150,w_150,e_sharpen:70/7318690080428.jpg", "brand": null, "price": "59,90 kr", "jfr Pris": 119.8}, {"name": "Clementiner Nadorcott", "img": "https://assets.icanet.se/q_auto,f_auto/c_lpad,h_150,w_150,e_sharpen:70/DR_5001984269.jpg", "brand": null, "price": "20 kr", "jfr Pris": 20.0}, {"name": "Kassler", "img": "https://assets.icanet.se/q_auto,f_auto/c_lpad,h_150,w_150,e_sharpen:70/2319277100008.jpg", "brand": "", "price": "2 f\u00f6r 49 kr", "jfr Pris": 49.9}, {"name": "Bakpotatis", "id": "5001984295", "brand": "ICA. Sverige", "price": "10 kr", "jfr Pris": 16.67, "img": "https://assets.icanet.se/q_auto,f_auto/c_lpad,h_150,w_150,e_sharpen:70/DR_5001984241.jpg", "displayVolume": "280-350 g"}, {"name": "Ekologiska apelsiner Navelinas", "id": "5001984292", "brand": "ICA I love eco. Spanien", "price": "20 kr", "jfr Pris": 20.0, "img": "https://assets.icanet.se/q_auto,f_auto/c_lpad,h_150,w_150,e_sharpen:70/DR_5001984295.jpg"}, {"name": "Galiameloner", "id": "5001984293", "brand": "Brasilien/Honduras/Costa Rica", "price": "20 kr", "jfr Pris": 20.0, "img": "https://assets.icanet.se/q_auto,f_auto/c_lpad,h_150,w_150,e_sharpen:70/DR_5001984292.jpg"}, {"name": "Jordgubbar i ask", "id": "5001984245", "brand": "ICA. Spanien", "price": "20 kr", "jfr Pris": 50.0, "img": "https://assets.icanet.se/q_auto,f_auto/c_lpad,h_150,w_150,e_sharpen:70/7318690162315.jpg", "displayVolume": "250 g"}, {"name": "Plommontomater i ask", "id": "5001984294", "brand": "ICA. Spanien", "price": "15 kr", "jfr Pris": 30.0, "img": "https://assets.icanet.se/q_auto,f_auto/c_lpad,h_150,w_150,e_sharpen:70/7318693309021.jpg", "displayVolume": "500 g"}, {"name": "Svartk\u00e5l i p\u00e5se, gr\u00f6nk\u00e5l i p\u00e5se", "id": "5001984246", "brand": "ICA. Spanien", "price": "20 kr", "jfr Pris": 100.0, "img": "https://assets.icanet.se/q_auto,f_auto/c_lpad,h_150,w_150,e_sharpen:70/DR_5001984294.jpg", "displayVolume": "200 g"}, {"name": "\u00c4pplen Royal Gala", "id": "5001984265", "brand": "ICA. Italien/Frankrike", "price": "15 kr", "jfr Pris": 15.0, "img": "https://assets.icanet.se/q_auto,f_auto/c_lpad,h_150,w_150,e_sharpen:70/DR_5001984246.jpg"}, {"name": "Levain, r\u00e5glevain, gr\u00f6tbr\u00f6d", "id": "5001984260", "brand": "P\u00e5gen", "price": "25 kr", "jfr Pris": 38.46, "img": "https://assets.icanet.se/q_auto,f_auto/c_lpad,h_150,w_150,e_sharpen:70/7311070008159.jpg", "displayVolume": "650-780 g"}, {"name": "Mjukt, h\u00e5rt tunnbr\u00f6d", "id": "5002022153", "brand": "Sarek, Gene, Abisko", "price": "35 kr", "jfr Pris": 53.03, "img": "https://assets.icanet.se/$y_h,$x_w,$pi_current:public_id/c_fit,w_$x,h_$y,u_7311800640109,x_$y_mul_-0.3,y_$x_mul_0.6,g_south_east/q_auto,f_auto/c_lpad,h_150,w_150,e_sharpen:70/7313830006795.jpg", "displayVolume": "330-375 g"}, {"name": "Chilimedaljong", "id": "5001984251", "brand": "ICA. Ursprung Sverige", "price": "36 kr", "jfr Pris": 123.0, "img": "https://assets.icanet.se/q_auto,f_auto/c_lpad,h_150,w_150,e_sharpen:70/7318690171034.jpg", "displayVolume": "300 g"}, {"name": "Ekologisk blandf\u00e4rs", "id": "5001984237", "brand": "Ursprung Sverige", "price": "46 kr", "jfr Pris": 93.8, "img": "https://assets.icanet.se/q_auto,f_auto/c_lpad,h_150,w_150,e_sharpen:70/7318690131144.jpg", "displayVolume": "500 g"}, {"name": "Falukorv", "id": "5001984297", "brand": "Lithells", "price": "55 kr", "jfr Pris": 34.38, "img": "https://assets.icanet.se/$y_h,$x_w,$pi_current:public_id/c_fit,w_$x,h_$y,u_7310620020139,x_$y_mul_-0.3,y_$x_mul_-0.3/q_auto,f_auto/c_lpad,h_150,w_150,e_sharpen:70/7310620020139.jpg", "displayVolume": "800 g"}, {"name": "Fl\u00e4skf\u00e4rs", "id": "5001984298", "brand": "Ursprung Sverige", "price": "27 kr", "jfr Pris": 55.8, "img": "https://assets.icanet.se/q_auto,f_auto/c_lpad,h_150,w_150,e_sharpen:70/7318690159179.jpg", "displayVolume": "500 g"}, {"name": "Fl\u00e4skl\u00e4gg", "id": "5001984239", "brand": "ICA. Ursprung Sverige", "price": "29 kr", "jfr Pris": 85.43, "img": "https://assets.icanet.se/q_auto,f_auto/c_lpad,h_150,w_150,e_sharpen:70/7318690142775.jpg", "displayVolume": "350 g"}, {"name": "Frysta skalade r\u00e4kor", "id": "5001984289", "brand": "Royal Greenland", "price": "79 kr", "jfr Pris": 114.14, "img": "https://assets.icanet.se/q_auto,f_auto/c_lpad,h_150,w_150,e_sharpen:70/5740301107132.jpg", "displayVolume": "700 g"}, {"name": "Gr\u00f6nsaksbullar", "id": "5001984235", "brand": "ICA", "price": "20 kr", "jfr Pris": 100.0, "img": "https://assets.icanet.se/q_auto,f_auto/c_lpad,h_150,w_150,e_sharpen:70/7318690111436.jpg", "displayVolume": "200 g"}, {"name": "Kalkonbr\u00f6stfil\u00e9, tunnskivad kalkonfil\u00e9", "id": "5001984282", "brand": "Ingelsta kalkon. Ursprung Sverige", "price": "149 kr", "jfr Pris": 149.0, "img": "https://assets.icanet.se/q_auto,f_auto/c_lpad,h_150,w_150,e_sharpen:70/2366056000004.jpg", "displayVolume": "Ca 450 g"}, {"name": "Kotlett med ben", "id": "5001984240", "brand": "Ursprung Sverige", "price": "69 kr", "jfr Pris": 69.9, "img": "https://assets.icanet.se/q_auto,f_auto/c_lpad,h_150,w_150,e_sharpen:70/DR_5001984282.jpg", "displayVolume": "Storpack"}, {"name": "K\u00f6ttbullar", "id": "5001984254", "brand": "Scan", "price": "39 kr", "jfr Pris": 88.67, "img": "https://assets.icanet.se/q_auto,f_auto/c_lpad,h_150,w_150,e_sharpen:70/DR_5001984240.jpg", "displayVolume": "450-500 g"}, {"name": "Mjukost i tub", "id": "5001984283", "brand": "Fj\u00e4llbrynt", "price": "22 kr", "jfr Pris": 91.6, "img": "https://assets.icanet.se/$y_h,$x_w,$pi_current:public_id/c_fit,w_$x,h_$y,u_7313160000197,x_$y_mul_-0.3,y_$x_mul_-0.3/q_auto,f_auto/c_lpad,h_150,w_150,e_sharpen:70/7313160000180.jpg", "displayVolume": "250 g"}, {"name": "N\u00f6tbog", "id": "5001984266", "brand": "Ursprung Sverige", "price": "89 kr", "jfr Pris": 89.9, "img": "https://assets.icanet.se/q_auto,f_auto/c_lpad,h_150,w_150,e_sharpen:70/2319117700009.jpg", "displayVolume": "Ca 1200 g"}, {"name": "Pr\u00e4st,Herrg\u00e5rd,Grev\u00e9,Svecia,Cheddar", "id": "5001984284", "brand": "Allerum", "price": "99 kr", "jfr Pris": 99.0, "img": "https://assets.icanet.se/q_auto,f_auto/c_lpad,h_150,w_150,e_sharpen:70/2324623300001.jpg", "displayVolume": "Ca 700 g"}, {"name": "Revbensspj\u00e4ll", "id": "5001984236", "brand": "Ursprung Sverige", "price": "49 kr", "jfr Pris": 49.9, "img": "https://assets.icanet.se/q_auto,f_auto/c_lpad,h_150,w_150,e_sharpen:70/2319118100006.jpg", "displayVolume": "Ca 1000 g"}, {"name": "Salami", "id": "5001984250", "brand": "Kotivara", "price": "35 kr", "jfr Pris": 218.75, "img": "https://assets.icanet.se/$y_h,$x_w,$pi_current:public_id/c_fit,w_$x,h_$y,u_6409630008518,x_$y_mul_-0.3,y_$x_mul_0.6,g_south_east/q_auto,f_auto/c_lpad,h_150,w_150,e_sharpen:70/6409630008525.jpg", "displayVolume": "80-120 g"}, {"name": "Varm-, wienerkorv", "id": "5001984280", "brand": "Lithells", "price": "42 kr", "jfr Pris": 57.2, "img": "https://assets.icanet.se/$y_h,$x_w,$pi_current:public_id/c_fit,w_$x,h_$y,u_7310620025417,x_$y_mul_-0.3,y_$x_mul_-0.3/q_auto,f_auto/c_lpad,h_150,w_150,e_sharpen:70/7310620025158.jpg", "displayVolume": "720-900 g"}, {"name": "Ekologisk Smoothie", "id": "5001984300", "brand": "Hipp", "price": "50 kr", "jfr Pris": 100.0, "img": "https://assets.icanet.se/q_auto,f_auto/c_lpad,h_150,w_150,e_sharpen:70/DR_5001984280.jpg", "displayVolume": "100 g"}, {"name": "Ekologisk tomatpur\u00e9", "id": "5001984304", "brand": "ICA I love eco", "price": "10 kr", "jfr Pris": 50.0, "img": "https://assets.icanet.se/q_auto,f_auto/c_lpad,h_150,w_150,e_sharpen:70/7318690007302.jpg", "displayVolume": "200 g"}, {"name": "Ekologiska blandade oliver", "id": "5001984252", "brand": "ICA I love eco", "price": "30 kr", "jfr Pris": 69.77, "img": "https://assets.icanet.se/$y_h,$x_w,$pi_current:public_id/c_fit,w_$x,h_$y,u_7318690007371,x_$y_mul_-0.3,y_$x_mul_0.6,g_south_east/q_auto,f_auto/c_lpad,h_150,w_150,e_sharpen:70/7318690007371.jpg", "displayVolume": "370 g"}, {"name": "Ekologiska b\u00f6nor, kik\u00e4rtor, linser", "id": "5001984274", "brand": "Zeta", "price": "20 kr", "jfr Pris": 43.48, "img": "https://assets.icanet.se/$y_h,$x_w,$pi_current:public_id/c_fit,w_$x,h_$y,u_7350002402955,x_$y_mul_-0.3,y_$x_mul_0.6,g_south_east/q_auto,f_auto/c_lpad,h_150,w_150,e_sharpen:70/7350002403440.jpg", "displayVolume": "380 g"}, {"name": "Fiber shot", "id": "5001984306", "brand": "Kiviks", "price": "25 kr", "jfr Pris": 50.0, "img": "https://assets.icanet.se/q_auto,f_auto/c_lpad,h_150,w_150,e_sharpen:70/7314720626307.jpg", "displayVolume": "50 cl"}, {"name": "Hoi sin s\u00e5s, Spring roll wrappers", "id": "5001984279", "brand": "Blue Dragon", "price": "20 kr", "jfr Pris": 100.0, "img": "https://assets.icanet.se/q_auto,f_auto/c_lpad,h_150,w_150,e_sharpen:70/DR_5001984306.jpg", "displayVolume": "134 g, 200 ml"}, {"name": "Linschips/b\u00e5gar", "id": "5001984277", "brand": "Estrella", "price": "32 kr", "jfr Pris": 160.0, "img": "https://assets.icanet.se/$y_h,$x_w,$pi_current:public_id/c_fit,w_$x,h_$y,u_7310532112236,x_$y_mul_-0.3,y_$x_mul_0.6,g_south_east/q_auto,f_auto/c_lpad,h_150,w_150,e_sharpen:70/7310532113073.jpg", "displayVolume": "110-125 g"}, {"name": "L\u00e4sk", "id": "5001984308", "brand": "Pepsi, Zingo, 7-up", "price": "25 kr", "jfr Pris": 8.33, "img": "https://assets.icanet.se/q_auto,f_auto/c_lpad,h_150,w_150,e_sharpen:70/DR_5001984277.jpg", "displayVolume": "150 cl"}, {"name": "Olivolja classico", "id": "5001984231", "brand": "Monini", "price": "59 kr", "jfr Pris": 79.87, "img": "https://assets.icanet.se/q_auto,f_auto/c_lpad,h_150,w_150,e_sharpen:70/0000080508816.jpg", "displayVolume": "750 ml"}, {"name": "Pasta", "id": "5001984248", "brand": "Zeta Casa Di Luca", "price": "10 kr", "jfr Pris": 25.0, "img": "https://assets.icanet.se/q_auto,f_auto/c_lpad,h_150,w_150,e_sharpen:70/7350002404584.jpg", "displayVolume": "400 g"}, {"name": "Soppa", "id": "5001984257", "brand": "Knorr", "price": "20 kr", "jfr Pris": 25.0, "img": "https://assets.icanet.se/$y_h,$x_w,$pi_current:public_id/c_fit,w_$x,h_$y,u_7310390001369,x_$y_mul_-0.3,y_$x_mul_0.6,g_south_east/q_auto,f_auto/c_lpad,h_150,w_150,e_sharpen:70/7310390001383.jpg", "displayVolume": "500-570 g, 570 ml"}, {"name": "Te 100-pack", "id": "5001984229", "brand": "Lipton", "price": "20 kr", "jfr Pris": 0.2, "img": "https://assets.icanet.se/$y_h,$x_w,$pi_current:public_id/c_fit,w_$x,h_$y,u_8712100679360,x_$y_mul_-0.3,y_$x_mul_-0.3/q_auto,f_auto/c_lpad,h_150,w_150,e_sharpen:70/3228881005373.jpg", "displayVolume": "100 st"}, {"name": "Creme Fraiche", "id": "5001984264", "brand": "Arla", "price": "20 kr", "jfr Pris": 40.0, "img": "https://assets.icanet.se/q_auto,f_auto/c_lpad,h_150,w_150,e_sharpen:70/7310865003775.jpg", "displayVolume": "5 dl"}, {"name": "H\u00e4lsofil", "id": "5001984267", "brand": "Verum", "price": "17 kr", "jfr Pris": 17.9, "img": "https://assets.icanet.se/q_auto,f_auto/c_lpad,h_150,w_150,e_sharpen:70/7310861012443.jpg", "displayVolume": "1 kg"}, {"name": "Juice", "id": "5001984263", "brand": "God Morgon", "price": "12 kr", "jfr Pris": 12.9, "img": "https://assets.icanet.se/$y_h,$x_w,$pi_current:public_id/c_fit,w_$x,h_$y,u_7310860007372,x_$y_mul_-0.3,y_$x_mul_0.6,g_south_east/q_auto,f_auto/c_lpad,h_150,w_150,e_sharpen:70/7310865074225.jpg", "displayVolume": "1 liter"}, {"name": "Kvarg", "id": "5001984281", "brand": "Lindahls", "price": "25 kr", "jfr Pris": 33.33, "img": "https://assets.icanet.se/q_auto,f_auto/c_lpad,h_150,w_150,e_sharpen:70/DR_5001984263.jpg", "displayVolume": "150 g"}, {"name": "Laktosfri mj\u00f6lk", "id": "5001984256", "brand": "Arla", "price": "10 kr", "jfr Pris": 10.0, "img": "https://assets.icanet.se/$y_h,$x_w,$pi_current:public_id/c_fit,w_$x,h_$y,u_7310865067883,x_$y_mul_-0.3,y_$x_mul_0.6,g_south_east/q_auto,f_auto/c_lpad,h_150,w_150,e_sharpen:70/7310865078216.jpg", "displayVolume": "1 liter"}, {"name": "Mild yoghurt", "id": "5001977465", "brand": "Arla", "price": "26 kr", "jfr Pris": 13.0, "img": "https://assets.icanet.se/$y_h,$x_w,$pi_current:public_id/c_fit,w_$x,h_$y,u_7310865866486,x_$y_mul_-0.3,y_$x_mul_0.6,g_south_east/q_auto,f_auto/c_lpad,h_150,w_150,e_sharpen:70/7310865879592.jpg", "displayVolume": "1 kg"}, {"name": "Elvisp", "id": "5002004047", "brand": "Bosch MFQ3010", "price": "199 kr", "jfr Pris": 199.0, "img": "https://assets.icanet.se/q_auto,f_auto/c_lpad,h_150,w_150,e_sharpen:70/4242002439808.jpg"}, {"name": "Fr\u00f6er", "id": "5001954074", "brand": null, "price": "K&#246;p 5 betala f&#246;r 4 kr", "jfr Pris": null, "img": "https://assets.icanet.se/q_auto,f_auto/c_lpad,h_150,w_150,e_sharpen:70/DR_5002004047.jpg"}, {"name": "F\u00f6rvaringsl\u00e5dor", "id": "5001977494", "brand": null, "price": "K&#246;p 3 betala f&#246;r 2 kr", "jfr Pris": null, "img": "https://assets.icanet.se/q_auto,f_auto/c_lpad,h_150,w_150,e_sharpen:70/6411760104107.jpg"}, {"name": "Mattermos", "id": "5001977448", "brand": "ICA", "price": "179 kr", "jfr Pris": null, "img": "https://assets.icanet.se/q_auto,f_auto/c_lpad,h_150,w_150,e_sharpen:70/7310380197560.jpg"}, {"name": "PET-flaska 3-pack", "id": "5001977496", "brand": "Sodastream", "price": "99 kr", "jfr Pris": null, "img": "https://assets.icanet.se/q_auto,f_auto/c_lpad,h_150,w_150,e_sharpen:70/8718309253783.jpg"}, {"name": "St\u00e5ltermos", "id": "5001977464", "brand": "ICA", "price": "129 kr", "jfr Pris": null, "img": "https://assets.icanet.se/q_auto,f_auto/c_lpad,h_150,w_150,e_sharpen:70/7310380468110.jpg"}, {"name": "Termosar", "id": "5001984278", "brand": "Thermos", "price": "25% kr", "jfr Pris": null, "img": "https://assets.icanet.se/$y_h,$x_w,$pi_current:public_id/c_fit,w_$x,h_$y,u_5010576835857,x_$y_mul_-0.3,y_$x_mul_-0.3/q_auto,f_auto/c_lpad,h_150,w_150,e_sharpen:70/5010576909176.jpg"}, {"name": "Flytande handtv\u00e5l refill", "id": "5001984255", "brand": "Dove", "price": "15 kr", "jfr Pris": 30.0, "img": "https://assets.icanet.se/$y_h,$x_w,$pi_current:public_id/c_fit,w_$x,h_$y,u_4000388179004,x_$y_mul_-0.3,y_$x_mul_0.6,g_south_east/q_auto,f_auto/c_lpad,h_150,w_150,e_sharpen:70/8710447482186.jpg", "displayVolume": "500 ml"}, {"name": "Schampo, balsam", "id": "5001984275", "brand": "TREsemm\u00e9", "price": "35 kr", "jfr Pris": 87.5, "img": "https://assets.icanet.se/q_auto,f_auto/c_lpad,h_150,w_150,e_sharpen:70/DR_5001984255.jpg", "displayVolume": "400-500 ml"}, {"name": "Tandborste, tandkr\u00e4m", "id": "5001984302", "brand": "Jordan", "price": "15 kr", "jfr Pris": 15.0, "img": "https://assets.icanet.se/q_auto,f_auto/c_lpad,h_150,w_150,e_sharpen:70/DR_5001984275.jpg", "displayVolume": "1-pack, 50-75 ml"}, {"name": "Fryst paj", "id": "5001984233", "brand": "ICA", "price": "30 kr", "jfr Pris": 68.18, "img": "https://assets.icanet.se/$y_h,$x_w,$pi_current:public_id/c_fit,w_$x,h_$y,u_7318690050797,x_$y_mul_-0.3,y_$x_mul_0.6,g_south_east/q_auto,f_auto/c_lpad,h_150,w_150,e_sharpen:70/7318690089575.jpg", "displayVolume": "220 g"}, {"name": "Fryst tunnskivad, tv\u00e5delad Kycklingfil\u00e9", "id": "5001984270", "brand": "Guldf\u00e5geln. Ursprung Sverige", "price": "69 kr", "jfr Pris": 99.86, "img": "https://assets.icanet.se/q_auto,f_auto/c_lpad,h_150,w_150,e_sharpen:70/7313940522857.jpg", "displayVolume": "700 g"}, {"name": "Frysta gr\u00f6nsaker", "id": "5001984249", "brand": "Apetit", "price": "15 kr", "jfr Pris": 30.0, "img": "https://assets.icanet.se/$y_h,$x_w,$pi_current:public_id/c_fit,w_$x,h_$y,u_6430104921484,x_$y_mul_-0.3,y_$x_mul_0.6,g_south_east/q_auto,f_auto/c_lpad,h_150,w_150,e_sharpen:70/6430104924102.jpg", "displayVolume": "500-600 g"}, {"name": "Glass stycksaker", "id": "5001977480", "brand": "GB Glace, Magnum, Ben &amp; Jerrys, Nocco, Barebells, Choice, Baba Succo", "price": "50% kr", "jfr Pris": null, "img": "https://assets.icanet.se/q_auto,f_auto/c_lpad,h_150,w_150,e_sharpen:70/DR_5001984249.jpg"}, {"name": "Blender Blend Force", "id": "5001984230", "brand": "OBH Nordica", "price": "399 kr", "jfr Pris": 399.0, "img": "https://assets.icanet.se/q_auto,f_auto/c_lpad,h_150,w_150,e_sharpen:70/3016661155918_1.jpg"}, {"name": "Duschcreme", "id": "5001977471", "brand": "Dubbeldusch", "price": "10 kr", "jfr Pris": 40.0, "img": "https://assets.icanet.se/$y_h,$x_w,$pi_current:public_id/c_fit,w_$x,h_$y,u_4005900553522,x_$y_mul_-0.3,y_$x_mul_-0.3/c_fit,w_$x,h_$y,u_4005900553584,x_$y_mul_-0.3,y_$x_mul_0.6,g_south_east/q_auto,f_auto/c_lpad,h_150,w_150,e_sharpen:70/4005900553645.jpg", "displayVolume": "250 ml"}, {"name": "Kolsyremaskin", "id": "5001977467", "brand": "Sodastream", "price": "699 kr", "jfr Pris": 699.0, "img": "https://assets.icanet.se/q_auto,f_auto/c_lpad,h_150,w_150,e_sharpen:70/8719128115283.jpg"}, {"name": "Lego", "id": "5001977431", "brand": "LEGO", "price": "149 kr", "jfr Pris": null, "img": "https://assets.icanet.se/q_auto,f_auto/c_lpad,h_150,w_150,e_sharpen:70/DR_5001977467.jpg"}, {"name": "Mattermos", "id": "5001977450", "brand": "ICA", "price": "129 kr", "jfr Pris": null, "img": "https://assets.icanet.se/q_auto,f_auto/c_lpad,h_150,w_150,e_sharpen:70/7331210164378.jpg"}, {"name": "V\u00e5ffelj\u00e4rn dubbelt", "id": "bottom-bar", "brand": "Wilfa", "price": "399 kr", "jfr Pris": 399.0, "img": "https://assets.icanet.se/q_auto,f_auto/c_lpad,h_150,w_150,e_sharpen:70/7044876027528.jpg"}]