[{"name": "Korv-, hamburgerbr\u00f6d", "img": "https://assets.icanet.se/$y_h,$x_w,$pi_current:public_id/c_fit,w_$x,h_$y,u_7311071336718,x_$y_mul_-0.3,y_$x_mul_-0.3/q_auto,f_auto/c_lpad,h_150,w_150,e_sharpen:70/7311071336442.jpg", "brand": null, "price": "2 f\u00f6r 35 kr", "jfr Pris": 42.07}, {"name": "Wettex", "img": "https://assets.icanet.se/q_auto,f_auto/c_lpad,h_150,w_150,e_sharpen:70/4023103118355.jpg", "brand": null, "price": "35 kr", "jfr Pris": 3.5}, {"name": "\u00c4gg Medium", "img": "https://assets.icanet.se/q_auto,f_auto/c_lpad,h_150,w_150,e_sharpen:70/7332489041551.jpg", "brand": null, "price": "30 kr", "jfr Pris": 2.0}, {"name": "Mineralvatten", "img": "https://assets.icanet.se/q_auto,f_auto/c_lpad,h_150,w_150,e_sharpen:70/DR_5002529675.jpg", "brand": null, "price": "4 f\u00f6r 20 kr", "jfr Pris": 3.33}, {"name": "Kryddkorv", "img": "https://assets.icanet.se/$y_h,$x_w,$pi_current:public_id/c_fit,w_$x,h_$y,u_7300208373009,x_$y_mul_-0.3,y_$x_mul_-0.3/q_auto,f_auto/c_lpad,h_150,w_150,e_sharpen:70/7300206706007.jpg", "brand": null, "price": "20 kr", "jfr Pris": 66.67}, {"name": "F\u00e4rgmixade sm\u00e5tomater i ask", "img": "https://assets.icanet.se/q_auto,f_auto/c_lpad,h_150,w_150,e_sharpen:70/7318690175629.jpg", "brand": null, "price": "15 kr", "jfr Pris": 42.86}, {"name": "Kotlett med ben", "img": "https://assets.icanet.se/q_auto,f_auto/c_lpad,h_150,w_150,e_sharpen:70/2319160300003.jpg", "brand": "", "price": "2 f\u00f6r 69 kr", "jfr Pris": 69.9}, {"name": "Gr\u00f6na k\u00e4rnfria druvor i ask", "id": "5002529671", "brand": "ICA. Spanien", "price": "20 kr", "jfr Pris": 40.0, "img": "https://assets.icanet.se/q_auto,f_auto/c_lpad,h_150,w_150,e_sharpen:70/7318693555800.jpg", "displayVolume": "500 g"}, {"name": "Minivattenmeloner", "id": "5002529659", "brand": "ICA. Spanien", "price": "15 kr", "jfr Pris": 15.0, "img": "https://assets.icanet.se/q_auto,f_auto/c_lpad,h_150,w_150,e_sharpen:70/2092434600008.jpg"}, {"name": "Pimientos de padron", "id": "5002529660", "brand": "ICA. Nederl\u00e4nderna/Spanien", "price": "20 kr", "jfr Pris": 80.0, "img": "https://assets.icanet.se/q_auto,f_auto/c_lpad,h_150,w_150,e_sharpen:70/7318690119944.jpg", "displayVolume": "250 g"}, {"name": "Plommon i korg", "id": "5002529673", "brand": "ICA. Spanien/Italien", "price": "25 kr", "jfr Pris": 31.25, "img": "https://assets.icanet.se/q_auto,f_auto/c_lpad,h_150,w_150,e_sharpen:70/7318690176305.jpg", "displayVolume": "800 g"}, {"name": "\u00c4pplen Pink Lady", "id": "5002529649", "brand": "Argentina/Chile/Sydafrika", "price": "29 kr", "jfr Pris": 29.9, "img": "https://assets.icanet.se/q_auto,f_auto/c_lpad,h_150,w_150,e_sharpen:70/2092412800000.jpg", "displayVolume": "320-416 g"}, {"name": "Fr\u00f6-, Fruktkusar", "id": "5002529703", "brand": "Fazer", "price": "22 kr", "jfr Pris": 54.52, "img": "https://assets.icanet.se/$y_h,$x_w,$pi_current:public_id/c_fit,w_$x,h_$y,u_7314871992009,x_$y_mul_-0.3,y_$x_mul_-0.3/q_auto,f_auto/c_lpad,h_150,w_150,e_sharpen:70/7314871990005.jpg", "displayVolume": "420-480 g"}, {"name": "Kex", "id": "5002529655", "brand": "TUC", "price": "30 kr", "jfr Pris": 75.0, "img": "https://assets.icanet.se/q_auto,f_auto/c_lpad,h_150,w_150,e_sharpen:70/DR_5002529703.jpg", "displayVolume": "100 g"}, {"name": "Vika Kn\u00e4ckebr\u00f6d", "id": "5002529664", "brand": "Leksandsbr\u00f6d", "price": "45 kr", "jfr Pris": 83.33, "img": "https://assets.icanet.se/q_auto,f_auto/c_lpad,h_150,w_150,e_sharpen:70/7391944111178.jpg", "displayVolume": "540 g"}, {"name": "Baby back ribs", "id": "5002529683", "brand": "ICA. Ursprung Sverige", "price": "59 kr", "jfr Pris": 126.11, "img": "https://assets.icanet.se/q_auto,f_auto/c_lpad,h_150,w_150,e_sharpen:70/7318690130499.jpg", "displayVolume": "475 g"}, {"name": "Benfri karr\u00e9", "id": "5002529681", "brand": "ICA. Ursprung Sverige", "price": "39 kr", "jfr Pris": 133.0, "img": "https://assets.icanet.se/q_auto,f_auto/c_lpad,h_150,w_150,e_sharpen:70/7318690134220.jpg", "displayVolume": "300 g"}, {"name": "Blandf\u00e4rs", "id": "5002529652", "brand": "ICA. Ursprung Sverige", "price": "39 kr", "jfr Pris": 79.8, "img": "https://assets.icanet.se/q_auto,f_auto/c_lpad,h_150,w_150,e_sharpen:70/7318690161967.jpg", "displayVolume": "500 g"}, {"name": "Borgm\u00e4star-, gr\u00e4dd-, kryddost", "id": "5002529705", "brand": "Boxholm", "price": "99 kr", "jfr Pris": 99.0, "img": "https://assets.icanet.se/q_auto,f_auto/c_lpad,h_150,w_150,e_sharpen:70/2378065400003.jpg", "displayVolume": "Ca 500-1000 g"}, {"name": "Brie-, getost", "id": "5002529684", "brand": "President", "price": "27 kr", "jfr Pris": 139.5, "img": "https://assets.icanet.se/$y_h,$x_w,$pi_current:public_id/c_fit,w_$x,h_$y,u_3228020114225,x_$y_mul_-0.3,y_$x_mul_0.6,g_south_east/q_auto,f_auto/c_lpad,h_150,w_150,e_sharpen:70/3228020232028.jpg", "displayVolume": "200 g"}, {"name": "Ekologisk kassler", "id": "5002529712", "brand": "Scan. Ursprung Sverige", "price": "119 kr", "jfr Pris": 119.0, "img": "https://assets.icanet.se/q_auto,f_auto/c_lpad,h_150,w_150,e_sharpen:70/2320029400000.jpg", "displayVolume": "Ca 600 g"}, {"name": "Familjefavoriter", "id": "5002529640", "brand": "Arla", "price": "69 kr", "jfr Pris": 69.9, "img": "https://assets.icanet.se/$y_h,$x_w,$pi_current:public_id/c_fit,w_$x,h_$y,u_2340379300003,x_$y_mul_-0.3,y_$x_mul_-0.3/c_fit,w_$x,h_$y,u_2340379500007,x_$y_mul_-0.3,y_$x_mul_0.6,g_south_east/q_auto,f_auto/c_lpad,h_150,w_150,e_sharpen:70/2340397400006.jpg", "displayVolume": "Ca 1,2 kg"}, {"name": "Feta, getost", "id": "5002529679", "brand": "Fontana", "price": "40 kr", "jfr Pris": 153.85, "img": "https://assets.icanet.se/$y_h,$x_w,$pi_current:public_id/c_fit,w_$x,h_$y,u_7316150976847,x_$y_mul_-0.3,y_$x_mul_-0.3/q_auto,f_auto/c_lpad,h_150,w_150,e_sharpen:70/7316150970340.jpg", "displayVolume": "130-150 g"}, {"name": "Fryst torskfil\u00e9", "id": "5002529642", "brand": "Royal Greenland", "price": "49 kr", "jfr Pris": 133.07, "img": "https://assets.icanet.se/q_auto,f_auto/c_lpad,h_150,w_150,e_sharpen:70/5740301151623.jpg", "displayVolume": "375 g"}, {"name": "F\u00e4rsk kycklingfil\u00e9, minutfil\u00e9 BBQ", "id": "5002529696", "brand": "Kronf\u00e5gel. Ursprung Sverige", "price": "115 kr", "jfr Pris": 159.72, "img": "https://assets.icanet.se/q_auto,f_auto/c_lpad,h_150,w_150,e_sharpen:70/7300328192009.jpg", "displayVolume": "720-800 g"}, {"name": "Kyld s\u00e5s, dressing", "id": "5002529682", "brand": "Eriks", "price": "35 kr", "jfr Pris": 102.94, "img": "https://assets.icanet.se/$y_h,$x_w,$pi_current:public_id/c_fit,w_$x,h_$y,u_7350042720040,x_$y_mul_-0.3,y_$x_mul_-0.3/q_auto,f_auto/c_lpad,h_150,w_150,e_sharpen:70/7350042720002.jpg", "displayVolume": "170-255 ml"}, {"name": "L\u00f6vbiff", "id": "5002529646", "brand": "ICA. Ursprung Sverige", "price": "169 kr", "jfr Pris": 169.0, "img": "https://assets.icanet.se/q_auto,f_auto/c_lpad,h_150,w_150,e_sharpen:70/2319143300006.jpg", "displayVolume": "Ca 1000 g"}, {"name": "Potatisgrat\u00e4ng, Rotfruktsgrat\u00e4ng", "id": "5002529713", "brand": "Peka", "price": "20 kr", "jfr Pris": 28.57, "img": "https://assets.icanet.se/$y_h,$x_w,$pi_current:public_id/c_fit,w_$x,h_$y,u_8711118013586,x_$y_mul_-0.3,y_$x_mul_0.6,g_south_east/q_auto,f_auto/c_lpad,h_150,w_150,e_sharpen:70/8711118013593.jpg", "displayVolume": "700-800 g"}, {"name": "Pr\u00e4st\u00ae, Herrg\u00e5rd\u00ae, Grev\u00e9\u00ae", "id": "5002529688", "brand": "Allerum", "price": "119 kr", "jfr Pris": 119.9, "img": "https://assets.icanet.se/$y_h,$x_w,$pi_current:public_id/c_fit,w_$x,h_$y,u_2324509000001,x_$y_mul_-0.3,y_$x_mul_-0.3/c_fit,w_$x,h_$y,u_2324613400001,x_$y_mul_-0.3,y_$x_mul_0.6,g_south_east/q_auto,f_auto/c_lpad,h_150,w_150,e_sharpen:70/2324623300001.jpg", "displayVolume": "Ca 700 g"}, {"name": "Revbenspj\u00e4ll", "id": "5002529687", "brand": "Ursprung Sverige", "price": "59 kr", "jfr Pris": 59.9, "img": "https://assets.icanet.se/q_auto,f_auto/c_lpad,h_150,w_150,e_sharpen:70/2319118100006.jpg", "displayVolume": "Ca 1000 g"}, {"name": "Skivad rostbiff", "id": "5002529685", "brand": "ICA. Ursprung Sverige", "price": "165 kr", "jfr Pris": 165.0, "img": "https://assets.icanet.se/q_auto,f_auto/c_lpad,h_150,w_150,e_sharpen:70/2319258700005.jpg", "displayVolume": "Ca 600 g"}, {"name": "Smashed burger", "id": "5002529650", "brand": "ICA Selection Holy Smoke. Ursprung Sverige", "price": "34 kr", "jfr Pris": 174.5, "img": "https://assets.icanet.se/q_auto,f_auto/c_lpad,h_150,w_150,e_sharpen:70/7318690173335.jpg", "displayVolume": "260 g"}, {"name": "Sm\u00f6rg\u00e5smat pl\u00e5nbok", "id": "5002529680", "brand": "L\u00f6nneberga", "price": "32 kr", "jfr Pris": 133.33, "img": "https://assets.icanet.se/$y_h,$x_w,$pi_current:public_id/c_fit,w_$x,h_$y,u_7312331808785,x_$y_mul_-0.3,y_$x_mul_-0.3/q_auto,f_auto/c_lpad,h_150,w_150,e_sharpen:70/7312331808204.jpg", "displayVolume": "120 g"}, {"name": "Varm-, wienerkorv", "id": "5002529704", "brand": "Lithells", "price": "45 kr", "jfr Pris": 60.0, "img": "https://assets.icanet.se/$y_h,$x_w,$pi_current:public_id/c_fit,w_$x,h_$y,u_7310620025417,x_$y_mul_-0.3,y_$x_mul_-0.3/q_auto,f_auto/c_lpad,h_150,w_150,e_sharpen:70/7310620025158.jpg", "displayVolume": "750-900 g"}, {"name": "\u00d6lkorv", "id": "5002566003", "brand": "Ridderheims", "price": "30 kr", "jfr Pris": 200.0, "img": "https://assets.icanet.se/$y_h,$x_w,$pi_current:public_id/c_fit,w_$x,h_$y,u_7392555502041,x_$y_mul_-0.3,y_$x_mul_-0.3/c_fit,w_$x,h_$y,u_7392555502041,x_$y_mul_-0.3,y_$x_mul_0.6,g_south_east/q_auto,f_auto/c_lpad,h_150,w_150,e_sharpen:70/7392555502089.jpg", "displayVolume": "50 g"}, {"name": "Alkoholfri \u00f6l", "id": "5002529700", "brand": "Wisby lager, Easy Rider, Ship full of IPA", "price": "33 kr", "jfr Pris": 33.33, "img": "https://assets.icanet.se/$y_h,$x_w,$pi_current:public_id/c_fit,w_$x,h_$y,u_7310401024851,x_$y_mul_-0.3,y_$x_mul_-0.3/c_fit,w_$x,h_$y,u_7310401034799,x_$y_mul_-0.3,y_$x_mul_0.6,g_south_east/q_auto,f_auto/c_lpad,h_150,w_150,e_sharpen:70/7310401039732.jpg", "displayVolume": "33 cl"}, {"name": "Chokladkaka", "id": "5002529706", "brand": "Marabou", "price": "30 kr", "jfr Pris": 81.08, "img": "https://assets.icanet.se/$y_h,$x_w,$pi_current:public_id/c_fit,w_$x,h_$y,u_7310511217402,x_$y_mul_-0.3,y_$x_mul_-0.3/q_auto,f_auto/c_lpad,h_150,w_150,e_sharpen:70/7310511210403.jpg", "displayVolume": "185-200 g"}, {"name": "Delichips, Cheez Deluxe", "id": "5002529648", "brand": "OLW", "price": "35 kr", "jfr Pris": 145.83, "img": "https://assets.icanet.se/$y_h,$x_w,$pi_current:public_id/c_fit,w_$x,h_$y,u_7340005406319,x_$y_mul_-0.3,y_$x_mul_-0.3/q_auto,f_auto/c_lpad,h_150,w_150,e_sharpen:70/7340005406036.jpg", "displayVolume": "120 g, 150 g"}, {"name": "Dryck av ciderkarakt\u00e4r", "id": "5002529657", "brand": "ICA", "price": "20 kr", "jfr Pris": 6.67, "img": "https://assets.icanet.se/$y_h,$x_w,$pi_current:public_id/c_fit,w_$x,h_$y,u_7318690106135,x_$y_mul_-0.3,y_$x_mul_-0.3/q_auto,f_auto/c_lpad,h_150,w_150,e_sharpen:70/7318690106128.jpg", "displayVolume": "150 cl"}, {"name": "Ekologiska krossade tomater", "id": "5002529709", "brand": "ICA I love eco", "price": "25 kr", "jfr Pris": 21.37, "img": "https://assets.icanet.se/$y_h,$x_w,$pi_current:public_id/c_fit,w_$x,h_$y,u_7318690113553,x_$y_mul_-0.3,y_$x_mul_-0.3/c_fit,w_$x,h_$y,u_7318690113553,x_$y_mul_-0.3,y_$x_mul_0.6,g_south_east/q_auto,f_auto/c_lpad,h_150,w_150,e_sharpen:70/7318690113553.jpg", "displayVolume": "390 g"}, {"name": "Energidryck", "id": "5002529658", "brand": "Monster", "price": "35 kr", "jfr Pris": 23.33, "img": "https://assets.icanet.se/$y_h,$x_w,$pi_current:public_id/c_fit,w_$x,h_$y,u_5060166694777,x_$y_mul_-0.3,y_$x_mul_-0.3/c_fit,w_$x,h_$y,u_5060335630971,x_$y_mul_-0.3,y_$x_mul_0.6,g_south_east/q_auto,f_auto/c_lpad,h_150,w_150,e_sharpen:70/5060335635716.jpg", "displayVolume": "500 ml"}, {"name": "Gott & Blandat", "id": "5002529653", "brand": "Malaco", "price": "40 kr", "jfr Pris": 78.43, "img": "https://assets.icanet.se/$y_h,$x_w,$pi_current:public_id/c_fit,w_$x,h_$y,u_7310350116249,x_$y_mul_-0.3,y_$x_mul_-0.3/c_fit,w_$x,h_$y,u_7310350106844,x_$y_mul_-0.3,y_$x_mul_0.6,g_south_east/q_auto,f_auto/c_lpad,h_150,w_150,e_sharpen:70/7310350106837.jpg", "displayVolume": "170-210 g"}, {"name": "Kattmat", "id": "5002529708", "brand": "ICA", "price": "129 kr", "jfr Pris": 26.88, "img": "https://assets.icanet.se/q_auto,f_auto/c_lpad,h_150,w_150,e_sharpen:70/7318690501817.jpg", "displayVolume": "4800 g"}, {"name": "L\u00e4sk", "id": "5002529711", "brand": "Coca-Cola, Fanta, Sprite", "price": "35 kr", "jfr Pris": 8.75, "img": "https://assets.icanet.se/$y_h,$x_w,$pi_current:public_id/c_fit,w_$x,h_$y,u_5000112650587,x_$y_mul_-0.3,y_$x_mul_-0.3/c_fit,w_$x,h_$y,u_5449000131843,x_$y_mul_-0.3,y_$x_mul_0.6,g_south_east/q_auto,f_auto/c_lpad,h_150,w_150,e_sharpen:70/7331040059219.jpg", "displayVolume": "2 liter"}, {"name": "L\u00e4sk", "id": "5002529699", "brand": "Schweppes", "price": "30 kr", "jfr Pris": 10.0, "img": "https://assets.icanet.se/$y_h,$x_w,$pi_current:public_id/c_fit,w_$x,h_$y,u_7310401043203,x_$y_mul_-0.3,y_$x_mul_-0.3/c_fit,w_$x,h_$y,u_7310401003306,x_$y_mul_-0.3,y_$x_mul_0.6,g_south_east/q_auto,f_auto/c_lpad,h_150,w_150,e_sharpen:70/7310401003245.jpg", "displayVolume": "150 cl"}, {"name": "Pasta", "id": "5002529693", "brand": "Zeta Casa Di Luca", "price": "26 kr", "jfr Pris": 32.5, "img": "https://assets.icanet.se/$y_h,$x_w,$pi_current:public_id/c_fit,w_$x,h_$y,u_7350027794936,x_$y_mul_-0.3,y_$x_mul_-0.3/q_auto,f_auto/c_lpad,h_150,w_150,e_sharpen:70/7350002404584.jpg", "displayVolume": "400 g"}, {"name": "Special K classic, red berries", "id": "5002573686", "brand": "Kellogg's", "price": "34 kr", "jfr Pris": 69.8, "img": "https://assets.icanet.se/$y_h,$x_w,$pi_current:public_id/c_fit,w_$x,h_$y,u_5053827153935,x_$y_mul_-0.3,y_$x_mul_-0.3/q_auto,f_auto/c_lpad,h_150,w_150,e_sharpen:70/5050083701344.jpg", "displayVolume": "500-600 g"}, {"name": "Bara yoghurt frukt & b\u00e4r", "id": "5002529666", "brand": "Sk\u00e5nemejerier", "price": "18 kr", "jfr Pris": 18.9, "img": "https://assets.icanet.se/$y_h,$x_w,$pi_current:public_id/c_fit,w_$x,h_$y,u_7310867531313,x_$y_mul_-0.3,y_$x_mul_-0.3/q_auto,f_auto/c_lpad,h_150,w_150,e_sharpen:70/7310867531306.jpg", "displayVolume": "1 kg"}, {"name": "Frukt, -safariyoghurt 6-pack", "id": "5002529692", "brand": "Yoplait", "price": "20 kr", "jfr Pris": 27.87, "img": "https://assets.icanet.se/q_auto,f_auto/c_lpad,h_150,w_150,e_sharpen:70/3329770058255.jpg", "displayVolume": "750 g"}, {"name": "Juice", "id": "5002529667", "brand": "God Morgon", "price": "28 kr", "jfr Pris": 14.0, "img": "https://assets.icanet.se/$y_h,$x_w,$pi_current:public_id/c_fit,w_$x,h_$y,u_7310865074225,x_$y_mul_-0.3,y_$x_mul_-0.3/q_auto,f_auto/c_lpad,h_150,w_150,e_sharpen:70/7310860007372.jpg", "displayVolume": "1 liter"}, {"name": "Keso", "id": "5002529645", "brand": "Arla", "price": "25 kr", "jfr Pris": 51.8, "img": "https://assets.icanet.se/q_auto,f_auto/c_lpad,h_150,w_150,e_sharpen:70/7310865008060.jpg", "displayVolume": "500 g"}, {"name": "Laktosfri mj\u00f6lk", "id": "5002529690", "brand": "Valio", "price": "35 kr", "jfr Pris": 11.67, "img": "https://assets.icanet.se/$y_h,$x_w,$pi_current:public_id/c_fit,w_$x,h_$y,u_6408432087851,x_$y_mul_-0.3,y_$x_mul_0.6,g_south_east/q_auto,f_auto/c_lpad,h_150,w_150,e_sharpen:70/6408432087851.jpg", "displayVolume": "1,5 liter"}, {"name": "Ris-, mannamellanm\u00e5l", "id": "5002529641", "brand": "Risifrutti", "price": "36 kr", "jfr Pris": 54.55, "img": "https://assets.icanet.se/q_auto,f_auto/c_lpad,h_150,w_150,e_sharpen:70/DR_5002529690.jpg", "displayVolume": "165-175 g"}, {"name": "Turkisk, grekisk yoghurt", "id": "5002566021", "brand": "Lindahls", "price": "24 kr", "jfr Pris": 24.9, "img": "https://assets.icanet.se/q_auto,f_auto/c_lpad,h_150,w_150,e_sharpen:70/7392672104104.jpg", "displayVolume": "1 kg"}, {"name": "Ballonger", "id": "5002529672", "brand": null, "price": "19 kr", "jfr Pris": 1.99, "img": "https://assets.icanet.se/q_auto,f_auto/c_lpad,h_150,w_150,e_sharpen:70/7391197562000.jpg", "displayVolume": "10-pack"}, {"name": "Orkid\u00e9", "id": "5002529669", "brand": null, "price": "129 kr", "jfr Pris": 64.5, "img": "https://assets.icanet.se/$y_h,$x_w,$pi_current:public_id/c_fit,w_$x,h_$y,u_7318690186052,x_$y_mul_-0.3,y_$x_mul_0.6,g_south_east/q_auto,f_auto/c_lpad,h_150,w_150,e_sharpen:70/7318690186052.jpg"}, {"name": "Rosor 9-pack R\u00f6da Korset", "id": "5002565998", "brand": "ICA. Fairtrade", "price": "59 kr", "jfr Pris": null, "img": "https://assets.icanet.se/q_auto,f_auto/c_lpad,h_150,w_150,e_sharpen:70/7318690165828.jpg"}, {"name": "Sk\u00e4rbr\u00e4da", "id": "5002566019", "brand": "ICA Basic", "price": "15 kr", "jfr Pris": null, "img": "https://assets.icanet.se/q_auto,f_auto/c_lpad,h_150,w_150,e_sharpen:70/7315340443107.jpg"}, {"name": "Sm\u00f6rkniv", "id": "5002566017", "brand": "ICA", "price": "15 kr", "jfr Pris": 7.5, "img": "https://assets.icanet.se/$y_h,$x_w,$pi_current:public_id/c_fit,w_$x,h_$y,u_7315340419805,x_$y_mul_-0.3,y_$x_mul_-0.3/q_auto,f_auto/c_lpad,h_150,w_150,e_sharpen:70/7315340419805.jpg"}, {"name": "Ugnsform", "id": "5002529656", "brand": "Pyrex", "price": "79 kr", "jfr Pris": null, "img": "https://assets.icanet.se/q_auto,f_auto/c_lpad,h_150,w_150,e_sharpen:70/3426470002981.jpg"}, {"name": "Ansiktsmask", "id": "5002529654", "brand": "Garnier", "price": "40 kr", "jfr Pris": 20.0, "img": "https://assets.icanet.se/$y_h,$x_w,$pi_current:public_id/c_fit,w_$x,h_$y,u_3600541945029,x_$y_mul_-0.3,y_$x_mul_-0.3/q_auto,f_auto/c_lpad,h_150,w_150,e_sharpen:70/3600541943766.jpg", "displayVolume": "1-pack"}, {"name": "Ansiktsv\u00e5rd", "id": "5002529678", "brand": "Garnier Skin Naturals, Active", "price": "20% kr", "jfr Pris": null, "img": "https://assets.icanet.se/$y_h,$x_w,$pi_current:public_id/c_fit,w_$x,h_$y,u_3600541358508,x_$y_mul_-0.3,y_$x_mul_0.6,g_south_east/q_auto,f_auto/c_lpad,h_150,w_150,e_sharpen:70/3600542044486.jpg", "displayVolume": "50-400 ml"}, {"name": "Fryst kycklingbr\u00f6stfil\u00e9", "id": "5002529643", "brand": "Guldf\u00e5geln. Ursprung Sverige", "price": "99 kr", "jfr Pris": 99.0, "img": "https://assets.icanet.se/q_auto,f_auto/c_lpad,h_150,w_150,e_sharpen:70/7313940522802.jpg", "displayVolume": "1000 g"}, {"name": "Fryst paj", "id": "5002529707", "brand": "ICA", "price": "35 kr", "jfr Pris": 79.55, "img": "https://assets.icanet.se/$y_h,$x_w,$pi_current:public_id/c_fit,w_$x,h_$y,u_7318690050797,x_$y_mul_-0.3,y_$x_mul_-0.3/c_fit,w_$x,h_$y,u_7318690050803,x_$y_mul_-0.3,y_$x_mul_0.6,g_south_east/q_auto,f_auto/c_lpad,h_150,w_150,e_sharpen:70/7318690089568.jpg", "displayVolume": "220 g"}, {"name": "Fryst sm\u00f6rdeg", "id": "5002529644", "brand": "ICA", "price": "20 kr", "jfr Pris": 50.0, "img": "https://assets.icanet.se/q_auto,f_auto/c_lpad,h_150,w_150,e_sharpen:70/7318690094562.jpg", "displayVolume": "400 g"}, {"name": "Frysta Enportionsr\u00e4tter a la carte/lean", "id": "5002529676", "brand": "Familjen Dafg\u00e5rd", "price": "55 kr", "jfr Pris": 78.57, "img": "https://assets.icanet.se/$y_h,$x_w,$pi_current:public_id/c_fit,w_$x,h_$y,u_7310960041863,x_$y_mul_-0.3,y_$x_mul_0.6,g_south_east/q_auto,f_auto/c_lpad,h_150,w_150,e_sharpen:70/7310960041962.jpg", "displayVolume": "350-420 g"}, {"name": "Glass flerpack", "id": "5002529697", "brand": "Fazer, Mars, Snickers", "price": "58 kr", "jfr Pris": 7.25, "img": "https://assets.icanet.se/$y_h,$x_w,$pi_current:public_id/c_fit,w_$x,h_$y,u_6430064404461,x_$y_mul_-0.3,y_$x_mul_-0.3/q_auto,f_auto/c_lpad,h_150,w_150,e_sharpen:70/5000159541459.jpg", "displayVolume": "4-8 pack"}, {"name": "Gr\u00e4ddglass", "id": "5002566013", "brand": "SIA Glass", "price": "50 kr", "jfr Pris": 25.0, "img": "https://assets.icanet.se/q_auto,f_auto/c_lpad,h_150,w_150,e_sharpen:70/DR_5002529697.jpg", "displayVolume": "0,5 liter"}, {"name": "Bakformar", "id": "5002566009", "brand": "Pyrex", "price": "49 kr", "jfr Pris": null, "img": "https://assets.icanet.se/$y_h,$x_w,$pi_current:public_id/c_fit,w_$x,h_$y,u_3426470276375,x_$y_mul_-0.3,y_$x_mul_-0.3/c_fit,w_$x,h_$y,u_3426470276351,x_$y_mul_-0.3,y_$x_mul_0.6,g_south_east/q_auto,f_auto/c_lpad,h_150,w_150,e_sharpen:70/3426470276337.jpg"}, {"name": "Eng\u00e5ngsfat 3-pack", "id": "5002566020", "brand": "ICA", "price": "39 kr", "jfr Pris": 13.3, "img": "https://assets.icanet.se/$y_h,$x_w,$pi_current:public_id/c_fit,w_$x,h_$y,u_7313136028385,x_$y_mul_-0.3,y_$x_mul_-0.3/q_auto,f_auto/c_lpad,h_150,w_150,e_sharpen:70/7313136028378.jpg"}, {"name": "Festpaket", "id": "5002566012", "brand": null, "price": "129 kr", "jfr Pris": null, "img": "https://assets.icanet.se/q_auto,f_auto/c_lpad,h_150,w_150,e_sharpen:70/7393885182088.jpg"}, {"name": "Fylld ljuslykta", "id": "5002566014", "brand": "ICA", "price": "25 kr", "jfr Pris": null, "img": "https://assets.icanet.se/q_auto,f_auto/c_lpad,h_150,w_150,e_sharpen:70/7331210168062.jpg"}, {"name": "F\u00f6rvaringsburkar", "id": "5002565961", "brand": "Gastromax", "price": "K&#246;p 4 betala f&#246;r 3 kr", "jfr Pris": null, "img": "https://assets.icanet.se/$y_h,$x_w,$pi_current:public_id/c_fit,w_$x,h_$y,u_6411767966432,x_$y_mul_-0.3,y_$x_mul_-0.3/c_fit,w_$x,h_$y,u_6411767946113,x_$y_mul_-0.3,y_$x_mul_0.6,g_south_east/q_auto,f_auto/c_lpad,h_150,w_150,e_sharpen:70/6411767920557.jpg"}, {"name": "Kr\u00e4fthatt", "id": "5002566011", "brand": null, "price": "19 kr", "jfr Pris": 4.98, "img": "https://assets.icanet.se/q_auto,f_auto/c_lpad,h_150,w_150,e_sharpen:70/7313130257392.jpg", "displayVolume": "4-pack"}, {"name": "Papperstallrikar", "id": "5002529647", "brand": "ICA", "price": "39 kr", "jfr Pris": 3.32, "img": "https://assets.icanet.se/q_auto,f_auto/c_lpad,h_150,w_150,e_sharpen:70/7313136028477.jpg", "displayVolume": "12-pack"}, {"name": "Schampo, balsam,flytande tv\u00e5l duschcreme", "id": "bottom-bar", "brand": "Barn\u00e4ngen", "price": "40 kr", "jfr Pris": 53.33, "img": "https://assets.icanet.se/$y_h,$x_w,$pi_current:public_id/c_fit,w_$x,h_$y,u_7332531107297,x_$y_mul_-0.3,y_$x_mul_-0.3/c_fit,w_$x,h_$y,u_7332531107297,x_$y_mul_-0.3,y_$x_mul_0.6,g_south_east/q_auto,f_auto/c_lpad,h_150,w_150,e_sharpen:70/7332531107754.jpg", "displayVolume": "250 ml"}]